{"name":"forest-semantic-v1","featureOrder":["isProdPath","isDevPath","isTestPath","isDocsPath","isExamplePath","isConfigFile","isSourceCodeFile","isLogFile","isIacFile","environmentHintOrd","valueLength","entropy","entropyLevelOrd","hasLivePrefix","hasTestPrefix","looksLikePlaceholder","isKnownTestValue","hasSecretVariableName","hasPublicVariableName","variableIntentOrd","hasExampleLanguage","hasPlaceholderLanguage","hasTestLanguage","hasSecretLanguage","hasProductionLanguage","hasDocumentationContext","storageExposureOrd","isPubliclyAccessible","assetCriticalityOrd","structurallyValid","luhnValid","formatValidForType","isPublicByDesign","isHighEntropySha","isAlreadyMasked","shapeContradictsType","isKnownTestVector","inTestDir","inFixturesDir","inSamplesDir","inBoilerplateDir","patternFrequency","isHighFrequencyPattern","hasPlaceholderIdentity","hasStructuralDomainNoun","typeSeverityNorm"],"trees":[{"f":26,"t":2.5,"l":{"f":9,"t":1.5,"l":{"leaf":0},"r":{"leaf":0.21428571428571427}},"r":{"f":34,"t":0.5,"l":{"f":29,"t":0.5,"l":{"leaf":0},"r":{"f":5,"t":0.5,"l":{"f":31,"t":0.5,"l":{"leaf":0},"r":{"f":33,"t":0.5,"l":{"leaf":0.9876543209876543},"r":{"leaf":0}}},"r":{"f":44,"t":0.5,"l":{"f":36,"t":0.5,"l":{"leaf":0.55},"r":{"leaf":0}},"r":{"leaf":0}}}},"r":{"leaf":0}}},{"f":29,"t":0.5,"l":{"leaf":0},"r":{"f":36,"t":0.5,"l":{"f":27,"t":0.5,"l":{"f":11,"t":4.609999999999999,"l":{"leaf":0},"r":{"leaf":1}},"r":{"f":5,"t":0.5,"l":{"f":42,"t":0.5,"l":{"f":44,"t":0.5,"l":{"leaf":0.5714285714285714},"r":{"leaf":0}},"r":{"f":19,"t":1.5,"l":{"leaf":1},"r":{"leaf":0.9627329192546584}}},"r":{"f":23,"t":0.5,"l":{"f":18,"t":0.5,"l":{"leaf":0.4444444444444444},"r":{"leaf":0.4}},"r":{"f":41,"t":6,"l":{"leaf":0.25},"r":{"leaf":1}}}}},"r":{"leaf":0}}},{"f":30,"t":0.5,"l":{"leaf":0},"r":{"f":27,"t":0.5,"l":{"leaf":0},"r":{"f":32,"t":0.5,"l":{"f":33,"t":0.5,"l":{"f":16,"t":0.5,"l":{"f":29,"t":0.5,"l":{"leaf":0},"r":{"leaf":0.8715596330275229}},"r":{"leaf":0}},"r":{"leaf":0}},"r":{"leaf":0}}}},{"f":27,"t":0.5,"l":{"f":12,"t":1.5,"l":{"leaf":0},"r":{"f":38,"t":0.5,"l":{"leaf":0.2},"r":{"leaf":0}}},"r":{"f":36,"t":0.5,"l":{"f":32,"t":0.5,"l":{"f":29,"t":0.5,"l":{"leaf":0},"r":{"f":7,"t":0.5,"l":{"f":12,"t":0.5,"l":{"leaf":0.9452054794520548},"r":{"leaf":0.7654320987654321}},"r":{"f":31,"t":0.5,"l":{"leaf":0},"r":{"leaf":1}}}},"r":{"leaf":0}},"r":{"leaf":0}}},{"f":2,"t":0.5,"l":{"f":27,"t":0.5,"l":{"f":12,"t":1.5,"l":{"leaf":0},"r":{"f":11,"t":4.609999999999999,"l":{"leaf":0},"r":{"leaf":1}}},"r":{"f":41,"t":4.5,"l":{"f":10,"t":38.5,"l":{"f":45,"t":0.7,"l":{"f":11,"t":1.81,"l":{"leaf":1},"r":{"leaf":0.05714285714285714}},"r":{"leaf":1}},"r":{"f":10,"t":151,"l":{"f":12,"t":1.5,"l":{"leaf":0},"r":{"leaf":0.6363636363636364}},"r":{"leaf":1}}},"r":{"f":11,"t":4.12,"l":{"f":10,"t":14,"l":{"f":11,"t":2.49,"l":{"leaf":0.6060606060606061},"r":{"leaf":0.8876404494382022}},"r":{"f":29,"t":0.5,"l":{"leaf":0},"r":{"leaf":0.7894736842105263}}},"r":{"leaf":1}}}},"r":{"leaf":0}},{"f":30,"t":0.5,"l":{"leaf":0},"r":{"f":26,"t":2.5,"l":{"f":23,"t":0.5,"l":{"leaf":0},"r":{"f":8,"t":0.5,"l":{"leaf":1},"r":{"leaf":0}}},"r":{"f":29,"t":0.5,"l":{"leaf":0},"r":{"f":41,"t":5.5,"l":{"f":11,"t":4.67,"l":{"f":31,"t":0.5,"l":{"leaf":0},"r":{"leaf":0.3902439024390244}},"r":{"f":10,"t":86.5,"l":{"leaf":1},"r":{"leaf":0.7142857142857143}}},"r":{"f":22,"t":0.5,"l":{"f":45,"t":0.575,"l":{"leaf":0.8870967741935484},"r":{"leaf":1}},"r":{"leaf":0}}}}}},{"f":27,"t":0.5,"l":{"leaf":0},"r":{"f":29,"t":0.5,"l":{"leaf":0},"r":{"f":24,"t":0.5,"l":{"f":44,"t":0.5,"l":{"f":42,"t":0.5,"l":{"f":19,"t":1.5,"l":{"leaf":0},"r":{"leaf":0.6585365853658537}},"r":{"f":7,"t":0.5,"l":{"leaf":0.9481481481481482},"r":{"leaf":1}}},"r":{"leaf":0}},"r":{"f":41,"t":4.5,"l":{"leaf":0},"r":{"leaf":1}}}}},{"f":29,"t":0.5,"l":{"leaf":0},"r":{"f":28,"t":1.5,"l":{"f":17,"t":0.5,"l":{"leaf":0},"r":{"f":11,"t":4.34,"l":{"leaf":0},"r":{"leaf":0.3333333333333333}}},"r":{"f":11,"t":3.445,"l":{"leaf":0.901840490797546},"r":{"f":33,"t":0.5,"l":{"f":16,"t":0.5,"l":{"f":12,"t":1.5,"l":{"leaf":0.2222222222222222},"r":{"leaf":0.7727272727272727}},"r":{"leaf":0}},"r":{"leaf":0}}}}},{"f":27,"t":0.5,"l":{"leaf":0},"r":{"f":25,"t":0.5,"l":{"f":31,"t":0.5,"l":{"leaf":0},"r":{"f":45,"t":0.75,"l":{"f":4,"t":0.5,"l":{"f":19,"t":1.5,"l":{"leaf":0.9230769230769231},"r":{"leaf":0.6262135922330098}},"r":{"leaf":0}},"r":{"leaf":1}}},"r":{"leaf":1}}},{"f":28,"t":1.5,"l":{"f":10,"t":36,"l":{"leaf":0},"r":{"leaf":1}},"r":{"f":31,"t":0.5,"l":{"leaf":0},"r":{"f":7,"t":0.5,"l":{"f":30,"t":0.5,"l":{"leaf":0},"r":{"f":4,"t":0.5,"l":{"f":34,"t":0.5,"l":{"leaf":0.7209302325581395},"r":{"leaf":0}},"r":{"leaf":0}}},"r":{"f":45,"t":0.7,"l":{"f":41,"t":31,"l":{"leaf":1},"r":{"leaf":0.8333333333333334}},"r":{"leaf":1}}}}},{"f":28,"t":1.5,"l":{"f":6,"t":0.5,"l":{"leaf":0},"r":{"f":17,"t":0.5,"l":{"leaf":0},"r":{"leaf":1}}},"r":{"f":4,"t":0.5,"l":{"f":31,"t":0.5,"l":{"leaf":0},"r":{"f":29,"t":0.5,"l":{"leaf":0},"r":{"f":10,"t":11.5,"l":{"leaf":1},"r":{"f":41,"t":8.5,"l":{"leaf":0.47692307692307695},"r":{"leaf":1}}}}},"r":{"leaf":0}}},{"f":27,"t":0.5,"l":{"f":41,"t":1.5,"l":{"leaf":0.75},"r":{"leaf":0}},"r":{"f":11,"t":3.325,"l":{"f":45,"t":0.75,"l":{"f":5,"t":0.5,"l":{"f":3,"t":0.5,"l":{"f":9,"t":2.5,"l":{"leaf":0.6708860759493671},"r":{"leaf":0.5}},"r":{"leaf":1}},"r":{"leaf":0}},"r":{"leaf":1}},"r":{"f":10,"t":44,"l":{"f":13,"t":0.5,"l":{"f":12,"t":1.5,"l":{"f":26,"t":3.5,"l":{"leaf":0},"r":{"leaf":0.17647058823529413}},"r":{"leaf":0.6666666666666666}},"r":{"leaf":1}},"r":{"f":17,"t":0.5,"l":{"leaf":1},"r":{"f":34,"t":0.5,"l":{"leaf":1},"r":{"leaf":0}}}}}},{"f":29,"t":0.5,"l":{"leaf":0},"r":{"f":4,"t":0.5,"l":{"f":26,"t":2.5,"l":{"f":10,"t":36,"l":{"leaf":0},"r":{"leaf":1}},"r":{"f":42,"t":0.5,"l":{"f":10,"t":22,"l":{"f":12,"t":0.5,"l":{"leaf":0.6428571428571429},"r":{"leaf":1}},"r":{"f":24,"t":0.5,"l":{"leaf":0.34615384615384615},"r":{"leaf":0}}},"r":{"f":3,"t":0.5,"l":{"f":31,"t":0.5,"l":{"leaf":0},"r":{"leaf":0.9770992366412213}},"r":{"leaf":1}}}},"r":{"leaf":0}}},{"f":26,"t":2.5,"l":{"f":23,"t":0.5,"l":{"leaf":0},"r":{"f":11,"t":4.609999999999999,"l":{"leaf":0},"r":{"leaf":1}}},"r":{"f":16,"t":0.5,"l":{"f":41,"t":4.5,"l":{"f":10,"t":22,"l":{"f":5,"t":0.5,"l":{"leaf":1},"r":{"f":44,"t":0.5,"l":{"leaf":1},"r":{"leaf":0}}},"r":{"f":0,"t":0.5,"l":{"leaf":0},"r":{"f":24,"t":0.5,"l":{"leaf":0.5454545454545454},"r":{"leaf":0}}}},"r":{"f":9,"t":2.5,"l":{"f":41,"t":28,"l":{"leaf":1},"r":{"f":45,"t":0.575,"l":{"leaf":0.7272727272727273},"r":{"leaf":0.5058823529411764}}},"r":{"f":45,"t":0.575,"l":{"leaf":0.8},"r":{"leaf":1}}}},"r":{"leaf":0}}},{"f":10,"t":14,"l":{"f":27,"t":0.5,"l":{"leaf":0},"r":{"f":4,"t":0.5,"l":{"f":45,"t":0.6499999999999999,"l":{"leaf":0.7682926829268293},"r":{"leaf":1}},"r":{"leaf":0}}},"r":{"f":4,"t":0.5,"l":{"f":27,"t":0.5,"l":{"f":6,"t":0.5,"l":{"leaf":0},"r":{"leaf":1}},"r":{"f":11,"t":4.645,"l":{"f":7,"t":0.5,"l":{"f":35,"t":0.5,"l":{"leaf":0.4215686274509804},"r":{"leaf":0}},"r":{"leaf":0}},"r":{"leaf":0.9259259259259259}}},"r":{"leaf":0}}},{"f":41,"t":4.5,"l":{"f":45,"t":0.7,"l":{"f":11,"t":4.66,"l":{"f":36,"t":0.5,"l":{"f":10,"t":7,"l":{"leaf":0.6666666666666666},"r":{"f":23,"t":0.5,"l":{"leaf":0.02702702702702703},"r":{"leaf":0}}},"r":{"leaf":0}},"r":{"f":6,"t":0.5,"l":{"leaf":0.8181818181818182},"r":{"leaf":1}}},"r":{"f":10,"t":8.5,"l":{"leaf":0},"r":{"leaf":1}}},"r":{"f":16,"t":0.5,"l":{"f":10,"t":10.5,"l":{"leaf":1},"r":{"f":29,"t":0.5,"l":{"leaf":0},"r":{"f":5,"t":0.5,"l":{"f":0,"t":0.5,"l":{"leaf":0.9787234042553191},"r":{"leaf":1}},"r":{"f":12,"t":1.5,"l":{"leaf":0},"r":{"leaf":1}}}}},"r":{"leaf":0}}},{"f":42,"t":0.5,"l":{"f":27,"t":0.5,"l":{"f":11,"t":4.34,"l":{"leaf":0},"r":{"leaf":0.25}},"r":{"f":11,"t":4.665,"l":{"f":17,"t":0.5,"l":{"f":0,"t":0.5,"l":{"leaf":0.5714285714285714},"r":{"f":18,"t":0.5,"l":{"leaf":0.34782608695652173},"r":{"leaf":0}}},"r":{"leaf":0}},"r":{"leaf":0.9375}}},"r":{"f":26,"t":2.5,"l":{"leaf":0},"r":{"f":10,"t":10.5,"l":{"leaf":1},"r":{"f":29,"t":0.5,"l":{"leaf":0},"r":{"f":26,"t":3.5,"l":{"f":17,"t":0.5,"l":{"leaf":0.8709677419354839},"r":{"leaf":0.7142857142857143}},"r":{"leaf":1}}}}}},{"f":22,"t":0.5,"l":{"f":45,"t":0.375,"l":{"leaf":0},"r":{"f":5,"t":0.5,"l":{"f":35,"t":0.5,"l":{"f":11,"t":4.29,"l":{"f":44,"t":0.5,"l":{"leaf":0.7256637168141593},"r":{"leaf":0}},"r":{"leaf":1}},"r":{"leaf":0}},"r":{"f":27,"t":0.5,"l":{"leaf":0},"r":{"f":32,"t":0.5,"l":{"f":34,"t":0.5,"l":{"leaf":0.6956521739130435},"r":{"leaf":0}},"r":{"leaf":0}}}}},"r":{"leaf":0}},{"f":27,"t":0.5,"l":{"leaf":0},"r":{"f":29,"t":0.5,"l":{"leaf":0},"r":{"f":32,"t":0.5,"l":{"f":34,"t":0.5,"l":{"f":44,"t":0.5,"l":{"f":22,"t":0.5,"l":{"leaf":0.9182692307692307},"r":{"leaf":0}},"r":{"leaf":0}},"r":{"leaf":0}},"r":{"leaf":0}}}},{"f":11,"t":4.66,"l":{"f":41,"t":5.5,"l":{"f":26,"t":3.5,"l":{"f":25,"t":0.5,"l":{"f":45,"t":0.7,"l":{"leaf":0},"r":{"f":12,"t":0.5,"l":{"leaf":0.2},"r":{"leaf":1}}},"r":{"leaf":0}},"r":{"f":10,"t":20.5,"l":{"leaf":1},"r":{"leaf":0}}},"r":{"f":11,"t":2.43,"l":{"f":11,"t":1.7000000000000002,"l":{"leaf":0},"r":{"f":25,"t":0.5,"l":{"leaf":0.125},"r":{"leaf":1}}},"r":{"f":5,"t":0.5,"l":{"leaf":0.6534090909090909},"r":{"f":23,"t":0.5,"l":{"leaf":0},"r":{"f":36,"t":0.5,"l":{"leaf":1},"r":{"leaf":0}}}}}},"r":{"f":11,"t":5.3,"l":{"f":17,"t":0.5,"l":{"leaf":1},"r":{"f":27,"t":0.5,"l":{"leaf":1},"r":{"f":42,"t":0.5,"l":{"f":11,"t":4.79,"l":{"leaf":0.6666666666666666},"r":{"leaf":1}},"r":{"leaf":1}}}},"r":{"f":11,"t":5.585,"l":{"leaf":0},"r":{"leaf":0.3333333333333333}}}},{"f":29,"t":0.5,"l":{"leaf":0},"r":{"f":11,"t":1.99,"l":{"f":45,"t":0.575,"l":{"leaf":0.25},"r":{"leaf":0}},"r":{"f":4,"t":0.5,"l":{"f":27,"t":0.5,"l":{"leaf":0},"r":{"f":32,"t":0.5,"l":{"f":42,"t":0.5,"l":{"leaf":0.7037037037037037},"r":{"leaf":0.9314285714285714}},"r":{"leaf":0}}},"r":{"leaf":0}}}},{"f":30,"t":0.5,"l":{"leaf":0},"r":{"f":45,"t":0.375,"l":{"leaf":0},"r":{"f":4,"t":0.5,"l":{"f":42,"t":0.5,"l":{"f":11,"t":3.9349999999999996,"l":{"f":10,"t":7,"l":{"leaf":0.4},"r":{"leaf":0.05}},"r":{"f":11,"t":5.279999999999999,"l":{"leaf":0.7647058823529411},"r":{"leaf":0.4}}},"r":{"f":45,"t":0.575,"l":{"f":29,"t":0.5,"l":{"leaf":0},"r":{"leaf":0.8108108108108109}},"r":{"f":29,"t":0.5,"l":{"leaf":0},"r":{"leaf":0.9626168224299065}}}},"r":{"leaf":0}}}},{"f":26,"t":2.5,"l":{"f":41,"t":1.5,"l":{"leaf":0.2},"r":{"leaf":0}},"r":{"f":30,"t":0.5,"l":{"leaf":0},"r":{"f":11,"t":2.96,"l":{"f":26,"t":3.5,"l":{"f":16,"t":0.5,"l":{"f":7,"t":0.5,"l":{"leaf":0},"r":{"leaf":1}},"r":{"leaf":0}},"r":{"leaf":0.8482142857142857}},"r":{"f":36,"t":0.5,"l":{"f":42,"t":0.5,"l":{"f":31,"t":0.5,"l":{"leaf":0},"r":{"leaf":0.5483870967741935}},"r":{"f":25,"t":0.5,"l":{"leaf":0.7258064516129032},"r":{"leaf":1}}},"r":{"leaf":0}}}}},{"f":28,"t":1.5,"l":{"f":11,"t":3.92,"l":{"leaf":0},"r":{"leaf":0.25}},"r":{"f":29,"t":0.5,"l":{"leaf":0},"r":{"f":26,"t":3.5,"l":{"f":45,"t":0.7,"l":{"f":10,"t":38.5,"l":{"f":41,"t":8.5,"l":{"leaf":0.12195121951219512},"r":{"leaf":0.8125}},"r":{"f":34,"t":0.5,"l":{"leaf":1},"r":{"leaf":0}}},"r":{"leaf":1}},"r":{"f":12,"t":0.5,"l":{"leaf":0.9875},"r":{"f":24,"t":0.5,"l":{"f":11,"t":3.01,"l":{"leaf":0},"r":{"leaf":0.9245283018867925}},"r":{"leaf":1}}}}}},{"f":45,"t":0.75,"l":{"f":2,"t":0.5,"l":{"f":26,"t":2.5,"l":{"leaf":0.1111111111111111},"r":{"f":10,"t":10.5,"l":{"leaf":1},"r":{"f":30,"t":0.5,"l":{"leaf":0},"r":{"f":9,"t":1,"l":{"leaf":1},"r":{"leaf":0.5343915343915344}}}}},"r":{"leaf":0}},"r":{"f":9,"t":1.5,"l":{"leaf":0},"r":{"leaf":1}}},{"f":27,"t":0.5,"l":{"f":12,"t":1.5,"l":{"leaf":0},"r":{"f":41,"t":1.5,"l":{"leaf":1},"r":{"leaf":0}}},"r":{"f":36,"t":0.5,"l":{"f":10,"t":10.5,"l":{"leaf":1},"r":{"f":32,"t":0.5,"l":{"f":44,"t":0.5,"l":{"f":31,"t":0.5,"l":{"leaf":0},"r":{"leaf":0.6181818181818182}},"r":{"leaf":0}},"r":{"leaf":0}}},"r":{"leaf":0}}},{"f":11,"t":1.99,"l":{"f":11,"t":1.5350000000000001,"l":{"leaf":0},"r":{"f":34,"t":0.5,"l":{"f":6,"t":0.5,"l":{"leaf":1},"r":{"leaf":0}},"r":{"leaf":0}}},"r":{"f":36,"t":0.5,"l":{"f":10,"t":14,"l":{"f":41,"t":43.5,"l":{"f":0,"t":0.5,"l":{"leaf":1},"r":{"f":42,"t":0.5,"l":{"leaf":0.6},"r":{"leaf":1}}},"r":{"f":3,"t":0.5,"l":{"leaf":0.6792452830188679},"r":{"leaf":1}}},"r":{"f":29,"t":0.5,"l":{"leaf":0},"r":{"f":8,"t":0.5,"l":{"f":41,"t":8.5,"l":{"leaf":0.3793103448275862},"r":{"leaf":1}},"r":{"leaf":0}}}},"r":{"leaf":0}}},{"f":10,"t":11.5,"l":{"f":26,"t":2.5,"l":{"leaf":0},"r":{"f":10,"t":10.5,"l":{"leaf":1},"r":{"f":9,"t":2.5,"l":{"f":29,"t":0.5,"l":{"leaf":0},"r":{"leaf":1}},"r":{"leaf":0.9333333333333333}}}},"r":{"f":28,"t":1.5,"l":{"f":10,"t":31.5,"l":{"leaf":0},"r":{"f":11,"t":4.34,"l":{"leaf":0},"r":{"leaf":0.5}}},"r":{"f":31,"t":0.5,"l":{"leaf":0},"r":{"f":30,"t":0.5,"l":{"leaf":0},"r":{"f":44,"t":0.5,"l":{"f":11,"t":4.529999999999999,"l":{"leaf":0.5363636363636364},"r":{"leaf":0.9285714285714286}},"r":{"leaf":0}}}}}},{"f":7,"t":0.5,"l":{"f":29,"t":0.5,"l":{"leaf":0},"r":{"f":11,"t":2.1550000000000002,"l":{"f":10,"t":8.5,"l":{"f":6,"t":0.5,"l":{"leaf":1},"r":{"leaf":0}},"r":{"leaf":0}},"r":{"f":41,"t":9.5,"l":{"f":8,"t":0.5,"l":{"f":16,"t":0.5,"l":{"leaf":0.6091954022988506},"r":{"leaf":0}},"r":{"leaf":0}},"r":{"f":41,"t":61,"l":{"leaf":1},"r":{"f":25,"t":0.5,"l":{"leaf":0.9642857142857143},"r":{"leaf":1}}}}}},"r":{"leaf":0.9795918367346939}},{"f":26,"t":2.5,"l":{"f":5,"t":0.5,"l":{"f":10,"t":36,"l":{"leaf":0},"r":{"leaf":1}},"r":{"leaf":0}},"r":{"f":44,"t":0.5,"l":{"f":30,"t":0.5,"l":{"leaf":0},"r":{"f":4,"t":0.5,"l":{"f":12,"t":0.5,"l":{"f":11,"t":2.415,"l":{"leaf":0.4782608695652174},"r":{"leaf":0.9026548672566371}},"r":{"f":29,"t":0.5,"l":{"leaf":0},"r":{"leaf":0.6990291262135923}}},"r":{"leaf":0}}},"r":{"leaf":0}}},{"f":28,"t":1.5,"l":{"f":11,"t":4.609999999999999,"l":{"leaf":0},"r":{"leaf":1}},"r":{"f":11,"t":4.645,"l":{"f":44,"t":0.5,"l":{"f":45,"t":0.75,"l":{"f":36,"t":0.5,"l":{"f":10,"t":23,"l":{"leaf":0.7049180327868853},"r":{"leaf":0.045454545454545456}},"r":{"leaf":0}},"r":{"leaf":1}},"r":{"leaf":0}},"r":{"f":11,"t":5.335,"l":{"leaf":1},"r":{"f":34,"t":0.5,"l":{"leaf":1},"r":{"leaf":0}}}}},{"f":29,"t":0.5,"l":{"leaf":0},"r":{"f":31,"t":0.5,"l":{"leaf":0},"r":{"f":27,"t":0.5,"l":{"f":17,"t":0.5,"l":{"leaf":0},"r":{"f":16,"t":0.5,"l":{"f":6,"t":0.5,"l":{"leaf":0},"r":{"leaf":1}},"r":{"leaf":0}}},"r":{"f":36,"t":0.5,"l":{"f":9,"t":2.5,"l":{"f":9,"t":1,"l":{"leaf":1},"r":{"leaf":0.9473684210526315}},"r":{"f":41,"t":8.5,"l":{"leaf":0.48717948717948717},"r":{"leaf":1}}},"r":{"leaf":0}}}}},{"f":29,"t":0.5,"l":{"leaf":0},"r":{"f":45,"t":0.375,"l":{"leaf":0},"r":{"f":4,"t":0.5,"l":{"f":28,"t":1.5,"l":{"f":5,"t":0.5,"l":{"f":12,"t":1.5,"l":{"leaf":0},"r":{"leaf":0.5714285714285714}},"r":{"leaf":0}},"r":{"f":44,"t":0.5,"l":{"f":41,"t":8.5,"l":{"leaf":0.5949367088607594},"r":{"leaf":1}},"r":{"leaf":0}}},"r":{"leaf":0}}}},{"f":27,"t":0.5,"l":{"f":10,"t":36,"l":{"leaf":0},"r":{"leaf":1}},"r":{"f":5,"t":0.5,"l":{"f":0,"t":0.5,"l":{"f":35,"t":0.5,"l":{"f":23,"t":0.5,"l":{"f":25,"t":0.5,"l":{"leaf":0.6166666666666667},"r":{"leaf":1}},"r":{"leaf":1}},"r":{"leaf":0}},"r":{"f":45,"t":0.7,"l":{"f":30,"t":0.5,"l":{"leaf":0},"r":{"f":19,"t":1.5,"l":{"leaf":1},"r":{"leaf":0.7142857142857143}}},"r":{"leaf":1}}},"r":{"f":11,"t":4.445,"l":{"f":13,"t":0.5,"l":{"leaf":0},"r":{"leaf":0.2}},"r":{"f":23,"t":0.5,"l":{"leaf":1},"r":{"leaf":0.875}}}}},{"f":29,"t":0.5,"l":{"leaf":0},"r":{"f":41,"t":4.5,"l":{"f":27,"t":0.5,"l":{"f":10,"t":29.5,"l":{"leaf":0},"r":{"leaf":0.3333333333333333}},"r":{"f":45,"t":0.7,"l":{"f":41,"t":1.5,"l":{"f":44,"t":0.5,"l":{"leaf":0.5555555555555556},"r":{"leaf":0}},"r":{"f":0,"t":0.5,"l":{"leaf":0},"r":{"leaf":0.05}}},"r":{"leaf":1}}},"r":{"f":16,"t":0.5,"l":{"f":45,"t":0.575,"l":{"f":12,"t":0.5,"l":{"f":0,"t":0.5,"l":{"leaf":0.8888888888888888},"r":{"leaf":1}},"r":{"leaf":0.7333333333333333}},"r":{"f":27,"t":0.5,"l":{"leaf":0},"r":{"leaf":1}}},"r":{"leaf":0}}}},{"f":28,"t":1.5,"l":{"leaf":0},"r":{"f":42,"t":0.5,"l":{"f":11,"t":4,"l":{"f":10,"t":8.5,"l":{"leaf":1},"r":{"f":5,"t":0.5,"l":{"leaf":0.18181818181818182},"r":{"leaf":0}}},"r":{"f":11,"t":5.285,"l":{"f":11,"t":4.79,"l":{"f":11,"t":4.31,"l":{"leaf":1},"r":{"leaf":0.25}},"r":{"leaf":1}},"r":{"leaf":0.3333333333333333}}},"r":{"f":16,"t":0.5,"l":{"f":9,"t":1,"l":{"leaf":1},"r":{"f":19,"t":1.5,"l":{"leaf":1},"r":{"f":23,"t":0.5,"l":{"leaf":0.6748768472906403},"r":{"leaf":1}}}},"r":{"leaf":0}}}},{"f":29,"t":0.5,"l":{"leaf":0},"r":{"f":28,"t":1.5,"l":{"f":10,"t":36,"l":{"leaf":0},"r":{"leaf":1}},"r":{"f":31,"t":0.5,"l":{"leaf":0},"r":{"f":22,"t":0.5,"l":{"f":5,"t":0.5,"l":{"f":7,"t":0.5,"l":{"leaf":0.9689922480620154},"r":{"leaf":1}},"r":{"f":4,"t":0.5,"l":{"leaf":0.5652173913043478},"r":{"leaf":0}}},"r":{"leaf":0}}}}},{"f":36,"t":0.5,"l":{"f":38,"t":0.5,"l":{"f":29,"t":0.5,"l":{"leaf":0},"r":{"f":5,"t":0.5,"l":{"f":27,"t":0.5,"l":{"f":4,"t":0.5,"l":{"leaf":0.2727272727272727},"r":{"leaf":0}},"r":{"f":0,"t":0.5,"l":{"leaf":0.950354609929078},"r":{"leaf":0.8780487804878049}}},"r":{"f":9,"t":2.5,"l":{"leaf":0},"r":{"f":23,"t":0.5,"l":{"leaf":0.28},"r":{"leaf":0.9166666666666666}}}}},"r":{"leaf":0}},"r":{"leaf":0}},{"f":27,"t":0.5,"l":{"f":2,"t":0.5,"l":{"f":3,"t":0.5,"l":{"f":23,"t":0.5,"l":{"leaf":0},"r":{"f":5,"t":0.5,"l":{"leaf":1},"r":{"leaf":0}}},"r":{"leaf":0}},"r":{"leaf":0}},"r":{"f":29,"t":0.5,"l":{"leaf":0},"r":{"f":31,"t":0.5,"l":{"leaf":0},"r":{"f":36,"t":0.5,"l":{"f":32,"t":0.5,"l":{"f":41,"t":8.5,"l":{"leaf":0.828125},"r":{"leaf":1}},"r":{"leaf":0}},"r":{"leaf":0}}}}},{"f":28,"t":1.5,"l":{"f":17,"t":0.5,"l":{"leaf":0},"r":{"f":10,"t":36,"l":{"leaf":0},"r":{"leaf":1}}},"r":{"f":32,"t":0.5,"l":{"f":10,"t":10.5,"l":{"leaf":1},"r":{"f":30,"t":0.5,"l":{"leaf":0},"r":{"f":11,"t":4.155,"l":{"f":10,"t":23,"l":{"leaf":0.6305732484076433},"r":{"leaf":0}},"r":{"f":41,"t":2,"l":{"leaf":0.7692307692307693},"r":{"leaf":1}}}}},"r":{"leaf":0}}},{"f":41,"t":4.5,"l":{"f":28,"t":1.5,"l":{"f":11,"t":4.615,"l":{"leaf":0},"r":{"leaf":1}},"r":{"f":41,"t":3.5,"l":{"f":12,"t":1.5,"l":{"f":5,"t":0.5,"l":{"f":10,"t":23.5,"l":{"leaf":1},"r":{"leaf":0}},"r":{"leaf":0}},"r":{"f":11,"t":5.279999999999999,"l":{"leaf":1},"r":{"leaf":0.6666666666666666}}},"r":{"leaf":0}}},"r":{"f":36,"t":0.5,"l":{"f":30,"t":0.5,"l":{"leaf":0},"r":{"f":4,"t":0.5,"l":{"f":41,"t":30.5,"l":{"f":41,"t":8.5,"l":{"leaf":0.775},"r":{"leaf":1}},"r":{"leaf":0.7045454545454546}},"r":{"leaf":0}}},"r":{"leaf":0}}},{"f":42,"t":0.5,"l":{"f":26,"t":2.5,"l":{"f":11,"t":4.609999999999999,"l":{"leaf":0},"r":{"leaf":1}},"r":{"f":45,"t":0.7,"l":{"f":23,"t":0.5,"l":{"f":44,"t":0.5,"l":{"f":24,"t":0.5,"l":{"leaf":0.45},"r":{"leaf":0}},"r":{"leaf":0}},"r":{"f":41,"t":2,"l":{"leaf":0.6},"r":{"leaf":0.25}}},"r":{"leaf":1}}},"r":{"f":28,"t":1.5,"l":{"leaf":0},"r":{"f":36,"t":0.5,"l":{"f":9,"t":1,"l":{"leaf":1},"r":{"f":18,"t":0.5,"l":{"f":10,"t":14,"l":{"leaf":0.8367346938775511},"r":{"leaf":0.43434343434343436}},"r":{"leaf":1}}},"r":{"leaf":0}}}},{"f":26,"t":2.5,"l":{"f":6,"t":0.5,"l":{"leaf":0},"r":{"leaf":0.5714285714285714}},"r":{"f":29,"t":0.5,"l":{"leaf":0},"r":{"f":4,"t":0.5,"l":{"f":31,"t":0.5,"l":{"leaf":0},"r":{"f":5,"t":0.5,"l":{"leaf":0.9819277108433735},"r":{"f":44,"t":0.5,"l":{"leaf":0.7222222222222222},"r":{"leaf":0}}}},"r":{"leaf":0}}}},{"f":28,"t":1.5,"l":{"f":11,"t":4.609999999999999,"l":{"leaf":0},"r":{"leaf":1}},"r":{"f":3,"t":0.5,"l":{"f":30,"t":0.5,"l":{"leaf":0},"r":{"f":29,"t":0.5,"l":{"leaf":0},"r":{"f":0,"t":0.5,"l":{"f":10,"t":28.5,"l":{"leaf":0.9516129032258065},"r":{"leaf":0}},"r":{"f":5,"t":0.5,"l":{"leaf":0.9024390243902439},"r":{"leaf":0.42857142857142855}}}}},"r":{"leaf":1}}},{"f":5,"t":0.5,"l":{"f":26,"t":2.5,"l":{"f":36,"t":0.5,"l":{"f":3,"t":0.5,"l":{"f":12,"t":1,"l":{"leaf":0},"r":{"leaf":0.3333333333333333}},"r":{"leaf":0}},"r":{"leaf":0}},"r":{"f":33,"t":0.5,"l":{"f":11,"t":2.74,"l":{"f":41,"t":34.5,"l":{"leaf":1},"r":{"leaf":0.7333333333333333}},"r":{"f":25,"t":0.5,"l":{"f":44,"t":0.5,"l":{"leaf":0.6379310344827587},"r":{"leaf":0}},"r":{"leaf":1}}},"r":{"leaf":0}}},"r":{"f":4,"t":0.5,"l":{"f":41,"t":8.5,"l":{"f":11,"t":4.8100000000000005,"l":{"f":12,"t":1.5,"l":{"f":41,"t":4.5,"l":{"leaf":0},"r":{"leaf":0.14285714285714285}},"r":{"f":17,"t":0.5,"l":{"leaf":0},"r":{"leaf":0.18181818181818182}}},"r":{"f":11,"t":5.66,"l":{"leaf":0.5},"r":{"leaf":1}}},"r":{"leaf":1}},"r":{"leaf":0}}},{"f":27,"t":0.5,"l":{"f":2,"t":0.5,"l":{"f":11,"t":4.615,"l":{"leaf":0},"r":{"leaf":1}},"r":{"leaf":0}},"r":{"f":10,"t":14,"l":{"f":31,"t":0.5,"l":{"leaf":0},"r":{"f":3,"t":0.5,"l":{"f":5,"t":0.5,"l":{"leaf":0.896551724137931},"r":{"leaf":0}},"r":{"leaf":1}}},"r":{"f":10,"t":38.5,"l":{"f":25,"t":0.5,"l":{"f":11,"t":3.4000000000000004,"l":{"f":30,"t":0.5,"l":{"leaf":0},"r":{"leaf":0.5689655172413793}},"r":{"f":32,"t":0.5,"l":{"leaf":0.2857142857142857},"r":{"leaf":0}}},"r":{"leaf":1}},"r":{"f":12,"t":1.5,"l":{"leaf":0},"r":{"f":3,"t":0.5,"l":{"f":34,"t":0.5,"l":{"leaf":1},"r":{"leaf":0}},"r":{"leaf":1}}}}}},{"f":5,"t":0.5,"l":{"f":31,"t":0.5,"l":{"leaf":0},"r":{"f":45,"t":0.375,"l":{"leaf":0},"r":{"f":35,"t":0.5,"l":{"f":10,"t":14,"l":{"f":9,"t":2.5,"l":{"leaf":0.8461538461538461},"r":{"leaf":1}},"r":{"f":12,"t":1.5,"l":{"leaf":0.449438202247191},"r":{"leaf":0.8666666666666667}}},"r":{"leaf":0}}}},"r":{"f":11,"t":4.075,"l":{"leaf":0},"r":{"f":32,"t":0.5,"l":{"leaf":0.75},"r":{"leaf":0}}}},{"f":29,"t":0.5,"l":{"leaf":0},"r":{"f":8,"t":0.5,"l":{"f":26,"t":3.5,"l":{"f":25,"t":0.5,"l":{"f":4,"t":0.5,"l":{"f":41,"t":8.5,"l":{"leaf":0.32075471698113206},"r":{"leaf":1}},"r":{"leaf":0}},"r":{"leaf":0}},"r":{"f":31,"t":0.5,"l":{"leaf":0},"r":{"f":41,"t":2,"l":{"leaf":0},"r":{"f":11,"t":2.96,"l":{"leaf":1},"r":{"leaf":0.9090909090909091}}}}},"r":{"leaf":0}}},{"f":28,"t":1.5,"l":{"f":6,"t":0.5,"l":{"leaf":0},"r":{"f":23,"t":0.5,"l":{"leaf":0},"r":{"leaf":1}}},"r":{"f":29,"t":0.5,"l":{"leaf":0},"r":{"f":31,"t":0.5,"l":{"leaf":0},"r":{"f":0,"t":0.5,"l":{"f":41,"t":9.5,"l":{"leaf":0.8181818181818182},"r":{"leaf":1}},"r":{"f":22,"t":0.5,"l":{"f":34,"t":0.5,"l":{"leaf":0.7922077922077922},"r":{"leaf":0}},"r":{"leaf":0}}}}}},{"f":26,"t":2.5,"l":{"f":23,"t":0.5,"l":{"leaf":0},"r":{"leaf":0.2}},"r":{"f":16,"t":0.5,"l":{"f":10,"t":10.5,"l":{"leaf":1},"r":{"f":12,"t":1.5,"l":{"f":5,"t":0.5,"l":{"f":44,"t":0.5,"l":{"leaf":0.5421686746987951},"r":{"leaf":0}},"r":{"f":42,"t":0.5,"l":{"leaf":0},"r":{"leaf":0.3333333333333333}}},"r":{"f":5,"t":0.5,"l":{"leaf":1},"r":{"leaf":0.8387096774193549}}}},"r":{"leaf":0}}},{"f":29,"t":0.5,"l":{"leaf":0},"r":{"f":41,"t":5.5,"l":{"f":27,"t":0.5,"l":{"f":23,"t":0.5,"l":{"leaf":0},"r":{"f":10,"t":17.5,"l":{"leaf":0},"r":{"leaf":0.25}}},"r":{"f":19,"t":1.5,"l":{"leaf":0},"r":{"f":36,"t":0.5,"l":{"f":34,"t":0.5,"l":{"leaf":0.6458333333333334},"r":{"leaf":0}},"r":{"leaf":0}}}},"r":{"f":38,"t":0.5,"l":{"f":4,"t":0.5,"l":{"f":22,"t":0.5,"l":{"f":10,"t":14,"l":{"leaf":0.9818181818181818},"r":{"leaf":0.8518518518518519}},"r":{"leaf":0}},"r":{"leaf":0}},"r":{"leaf":0}}}},{"f":28,"t":1.5,"l":{"f":12,"t":1.5,"l":{"leaf":0},"r":{"f":28,"t":0.5,"l":{"leaf":0},"r":{"f":2,"t":0.5,"l":{"leaf":1},"r":{"leaf":0}}}},"r":{"f":5,"t":0.5,"l":{"f":31,"t":0.5,"l":{"leaf":0},"r":{"f":29,"t":0.5,"l":{"leaf":0},"r":{"f":7,"t":0.5,"l":{"f":42,"t":0.5,"l":{"leaf":0.6363636363636364},"r":{"leaf":0.9925373134328358}},"r":{"leaf":1}}}},"r":{"f":10,"t":38.5,"l":{"f":42,"t":0.5,"l":{"f":17,"t":0.5,"l":{"leaf":0},"r":{"leaf":0.1111111111111111}},"r":{"f":16,"t":0.5,"l":{"leaf":0.7142857142857143},"r":{"leaf":0}}},"r":{"leaf":0.7333333333333333}}}},{"f":30,"t":0.5,"l":{"leaf":0},"r":{"f":36,"t":0.5,"l":{"f":26,"t":2.5,"l":{"f":23,"t":0.5,"l":{"leaf":0},"r":{"f":12,"t":1.5,"l":{"leaf":0},"r":{"leaf":1}}},"r":{"f":10,"t":10.5,"l":{"leaf":1},"r":{"f":3,"t":0.5,"l":{"f":0,"t":0.5,"l":{"leaf":0.5555555555555556},"r":{"leaf":0.6829268292682927}},"r":{"leaf":1}}}},"r":{"leaf":0}}},{"f":29,"t":0.5,"l":{"leaf":0},"r":{"f":27,"t":0.5,"l":{"f":17,"t":0.5,"l":{"leaf":0},"r":{"f":6,"t":0.5,"l":{"leaf":0},"r":{"leaf":1}}},"r":{"f":10,"t":23,"l":{"f":0,"t":0.5,"l":{"f":3,"t":0.5,"l":{"f":45,"t":0.575,"l":{"leaf":0.9354838709677419},"r":{"leaf":1}},"r":{"leaf":1}},"r":{"f":10,"t":14,"l":{"f":11,"t":2.41,"l":{"leaf":0},"r":{"leaf":0.8529411764705882}},"r":{"f":17,"t":0.5,"l":{"leaf":0},"r":{"leaf":0.8}}}},"r":{"f":34,"t":0.5,"l":{"f":16,"t":0.5,"l":{"f":31,"t":0.5,"l":{"leaf":0},"r":{"leaf":0.7142857142857143}},"r":{"leaf":0}},"r":{"leaf":0}}}}},{"f":11,"t":4.529999999999999,"l":{"f":26,"t":2.5,"l":{"leaf":0},"r":{"f":36,"t":0.5,"l":{"f":31,"t":0.5,"l":{"leaf":0},"r":{"f":45,"t":0.75,"l":{"f":33,"t":0.5,"l":{"leaf":0.6135265700483091},"r":{"leaf":0}},"r":{"leaf":1}}},"r":{"leaf":0}}},"r":{"f":18,"t":0.5,"l":{"f":11,"t":5.279999999999999,"l":{"f":41,"t":2.5,"l":{"leaf":1},"r":{"f":10,"t":40,"l":{"leaf":0.8333333333333334},"r":{"leaf":1}}},"r":{"leaf":0.6666666666666666}},"r":{"leaf":1}}},{"f":28,"t":1.5,"l":{"f":42,"t":0.5,"l":{"f":5,"t":0.5,"l":{"f":23,"t":0.5,"l":{"leaf":0},"r":{"leaf":1}},"r":{"leaf":0}},"r":{"leaf":0}},"r":{"f":30,"t":0.5,"l":{"leaf":0},"r":{"f":4,"t":0.5,"l":{"f":32,"t":0.5,"l":{"f":10,"t":21,"l":{"f":12,"t":1.5,"l":{"leaf":0.8269230769230769},"r":{"leaf":1}},"r":{"f":12,"t":1.5,"l":{"leaf":0.4098360655737705},"r":{"leaf":0.84375}}},"r":{"leaf":0}},"r":{"leaf":0}}}},{"f":41,"t":4.5,"l":{"f":28,"t":1.5,"l":{"f":11,"t":4.34,"l":{"leaf":0},"r":{"leaf":0.25}},"r":{"f":24,"t":0.5,"l":{"f":18,"t":0.5,"l":{"f":33,"t":0.5,"l":{"f":31,"t":0.5,"l":{"leaf":0},"r":{"leaf":0.8125}},"r":{"leaf":0}},"r":{"leaf":0}},"r":{"leaf":0}}},"r":{"f":4,"t":0.5,"l":{"f":29,"t":0.5,"l":{"leaf":0},"r":{"f":16,"t":0.5,"l":{"f":0,"t":0.5,"l":{"f":27,"t":0.5,"l":{"leaf":0},"r":{"leaf":0.96875}},"r":{"f":7,"t":0.5,"l":{"leaf":0.65},"r":{"leaf":1}}},"r":{"leaf":0}}},"r":{"leaf":0}}},{"f":31,"t":0.5,"l":{"leaf":0},"r":{"f":41,"t":4.5,"l":{"f":11,"t":3.9349999999999996,"l":{"f":9,"t":1.5,"l":{"leaf":0},"r":{"f":41,"t":2,"l":{"leaf":0.5},"r":{"f":9,"t":2.5,"l":{"leaf":0.11764705882352941},"r":{"leaf":0}}}},"r":{"f":24,"t":0.5,"l":{"f":13,"t":0.5,"l":{"f":10,"t":35.5,"l":{"leaf":0},"r":{"leaf":0.8}},"r":{"leaf":1}},"r":{"leaf":0}}},"r":{"f":28,"t":1.5,"l":{"leaf":0},"r":{"f":10,"t":14,"l":{"f":29,"t":0.5,"l":{"leaf":0},"r":{"leaf":1}},"r":{"f":36,"t":0.5,"l":{"f":3,"t":0.5,"l":{"leaf":0.5428571428571428},"r":{"leaf":1}},"r":{"leaf":0}}}}}},{"f":2,"t":0.5,"l":{"f":4,"t":0.5,"l":{"f":36,"t":0.5,"l":{"f":41,"t":4.5,"l":{"f":41,"t":1.5,"l":{"f":44,"t":0.5,"l":{"leaf":0.7142857142857143},"r":{"leaf":0}},"r":{"f":11,"t":5.175,"l":{"leaf":0.12903225806451613},"r":{"leaf":1}}},"r":{"f":41,"t":30.5,"l":{"f":41,"t":8.5,"l":{"leaf":0.8157894736842105},"r":{"leaf":1}},"r":{"f":26,"t":3.5,"l":{"leaf":0.7272727272727273},"r":{"leaf":0.5877862595419847}}}},"r":{"leaf":0}},"r":{"leaf":0}},"r":{"leaf":0}},{"f":10,"t":14,"l":{"f":5,"t":0.5,"l":{"f":27,"t":0.5,"l":{"leaf":0},"r":{"f":41,"t":43.5,"l":{"leaf":1},"r":{"f":11,"t":2.4450000000000003,"l":{"f":11,"t":2.39,"l":{"leaf":0.5},"r":{"leaf":0}},"r":{"f":11,"t":2.8200000000000003,"l":{"leaf":0.8157894736842105},"r":{"leaf":0.6666666666666666}}}}},"r":{"leaf":0}},"r":{"f":4,"t":0.5,"l":{"f":29,"t":0.5,"l":{"leaf":0},"r":{"f":41,"t":9.5,"l":{"f":10,"t":38.5,"l":{"f":9,"t":2.5,"l":{"leaf":0},"r":{"leaf":0.19047619047619047}},"r":{"f":41,"t":2,"l":{"leaf":0.8181818181818182},"r":{"leaf":1}}},"r":{"leaf":1}}},"r":{"leaf":0}}},{"f":5,"t":0.5,"l":{"f":42,"t":0.5,"l":{"f":25,"t":0.5,"l":{"f":9,"t":2.5,"l":{"f":12,"t":0.5,"l":{"f":45,"t":0.675,"l":{"leaf":1},"r":{"leaf":0}},"r":{"f":12,"t":1.5,"l":{"leaf":0},"r":{"leaf":0.5}}},"r":{"leaf":0.25}},"r":{"leaf":0}},"r":{"f":7,"t":0.5,"l":{"f":25,"t":0.5,"l":{"f":30,"t":0.5,"l":{"leaf":0},"r":{"f":10,"t":19,"l":{"leaf":0.8181818181818182},"r":{"leaf":0.4375}}},"r":{"f":26,"t":3,"l":{"leaf":0},"r":{"leaf":1}}},"r":{"leaf":0.8888888888888888}}},"r":{"f":11,"t":3.5,"l":{"leaf":0},"r":{"f":11,"t":4.645,"l":{"f":10,"t":26,"l":{"f":4,"t":0.5,"l":{"leaf":1},"r":{"leaf":0}},"r":{"f":32,"t":0.5,"l":{"f":24,"t":0.5,"l":{"leaf":0},"r":{"leaf":1}},"r":{"leaf":0}}},"r":{"f":11,"t":5.305,"l":{"leaf":1},"r":{"leaf":0.375}}}}},{"f":27,"t":0.5,"l":{"f":41,"t":1.5,"l":{"leaf":0.8333333333333334},"r":{"leaf":0}},"r":{"f":41,"t":4.5,"l":{"f":41,"t":3.5,"l":{"f":45,"t":0.7,"l":{"f":31,"t":0.5,"l":{"leaf":0},"r":{"f":16,"t":0.5,"l":{"leaf":0.6296296296296297},"r":{"leaf":0}}},"r":{"leaf":1}},"r":{"leaf":0}},"r":{"f":4,"t":0.5,"l":{"f":30,"t":0.5,"l":{"leaf":0},"r":{"f":29,"t":0.5,"l":{"leaf":0},"r":{"f":3,"t":0.5,"l":{"leaf":0.9607843137254902},"r":{"leaf":1}}}},"r":{"leaf":0}}}},{"f":4,"t":0.5,"l":{"f":28,"t":1.5,"l":{"f":11,"t":4.609999999999999,"l":{"leaf":0},"r":{"leaf":1}},"r":{"f":30,"t":0.5,"l":{"leaf":0},"r":{"f":9,"t":1,"l":{"leaf":1},"r":{"f":0,"t":0.5,"l":{"f":29,"t":0.5,"l":{"leaf":0},"r":{"leaf":0.9469026548672567}},"r":{"f":32,"t":0.5,"l":{"leaf":0.6619718309859155},"r":{"leaf":0}}}}}},"r":{"leaf":0}},{"f":28,"t":1.5,"l":{"f":10,"t":36,"l":{"leaf":0},"r":{"leaf":1}},"r":{"f":32,"t":0.5,"l":{"f":29,"t":0.5,"l":{"leaf":0},"r":{"f":31,"t":0.5,"l":{"leaf":0},"r":{"f":34,"t":0.5,"l":{"f":36,"t":0.5,"l":{"leaf":0.9479166666666666},"r":{"leaf":0}},"r":{"leaf":0}}}},"r":{"leaf":0}}},{"f":27,"t":0.5,"l":{"f":12,"t":1.5,"l":{"leaf":0},"r":{"f":41,"t":2,"l":{"leaf":1},"r":{"leaf":0}}},"r":{"f":16,"t":0.5,"l":{"f":3,"t":0.5,"l":{"f":30,"t":0.5,"l":{"leaf":0},"r":{"f":24,"t":0.5,"l":{"f":31,"t":0.5,"l":{"leaf":0},"r":{"leaf":0.7297297297297297}},"r":{"f":23,"t":0.5,"l":{"leaf":0},"r":{"leaf":0.2857142857142857}}}},"r":{"leaf":1}},"r":{"leaf":0}}},{"f":4,"t":0.5,"l":{"f":30,"t":0.5,"l":{"leaf":0},"r":{"f":42,"t":0.5,"l":{"f":26,"t":2.5,"l":{"f":41,"t":1.5,"l":{"leaf":0.5},"r":{"leaf":0}},"r":{"f":34,"t":0.5,"l":{"f":32,"t":0.5,"l":{"leaf":0.6896551724137931},"r":{"leaf":0}},"r":{"leaf":0}}},"r":{"f":13,"t":0.5,"l":{"f":0,"t":0.5,"l":{"leaf":0.7341040462427746},"r":{"f":7,"t":0.5,"l":{"leaf":0.875},"r":{"leaf":1}}},"r":{"leaf":0}}}},"r":{"leaf":0}},{"f":28,"t":1.5,"l":{"f":6,"t":0.5,"l":{"leaf":0},"r":{"leaf":0.5}},"r":{"f":29,"t":0.5,"l":{"leaf":0},"r":{"f":36,"t":0.5,"l":{"f":32,"t":0.5,"l":{"f":33,"t":0.5,"l":{"f":9,"t":2.5,"l":{"leaf":0.9236641221374046},"r":{"leaf":0.8115942028985508}},"r":{"leaf":0}},"r":{"leaf":0}},"r":{"leaf":0}}}},{"f":41,"t":4.5,"l":{"f":4,"t":0.5,"l":{"f":12,"t":1.5,"l":{"f":7,"t":0.5,"l":{"f":23,"t":0.5,"l":{"f":41,"t":2.5,"l":{"leaf":0},"r":{"leaf":0.16666666666666666}},"r":{"leaf":0}},"r":{"leaf":0.3333333333333333}},"r":{"f":11,"t":5.66,"l":{"f":11,"t":5.225,"l":{"f":24,"t":0.5,"l":{"leaf":0.875},"r":{"leaf":0}},"r":{"leaf":0}},"r":{"leaf":1}}},"r":{"leaf":0}},"r":{"f":26,"t":2.5,"l":{"leaf":0},"r":{"f":25,"t":0.5,"l":{"f":11,"t":3.165,"l":{"f":35,"t":0.5,"l":{"leaf":0.5828571428571429},"r":{"leaf":0}},"r":{"f":4,"t":0.5,"l":{"f":29,"t":0.5,"l":{"leaf":0},"r":{"leaf":1}},"r":{"leaf":0}}},"r":{"leaf":1}}}},{"f":26,"t":2.5,"l":{"f":11,"t":4.34,"l":{"leaf":0},"r":{"leaf":0.5}},"r":{"f":29,"t":0.5,"l":{"leaf":0},"r":{"f":34,"t":0.5,"l":{"f":16,"t":0.5,"l":{"f":26,"t":3.5,"l":{"f":41,"t":8.5,"l":{"leaf":0.48484848484848486},"r":{"leaf":1}},"r":{"f":10,"t":27.5,"l":{"leaf":0.9545454545454546},"r":{"leaf":0.6666666666666666}}},"r":{"leaf":0}},"r":{"leaf":0}}}},{"f":10,"t":14,"l":{"f":26,"t":2.5,"l":{"leaf":0},"r":{"f":31,"t":0.5,"l":{"leaf":0},"r":{"f":11,"t":2.49,"l":{"f":29,"t":0.5,"l":{"leaf":0},"r":{"f":42,"t":0.5,"l":{"leaf":0.8},"r":{"leaf":1}}},"r":{"f":45,"t":0.575,"l":{"f":41,"t":38,"l":{"leaf":1},"r":{"leaf":0.975609756097561}},"r":{"f":32,"t":0.5,"l":{"leaf":1},"r":{"leaf":0}}}}}},"r":{"f":26,"t":2.5,"l":{"f":6,"t":0.5,"l":{"leaf":0},"r":{"leaf":1}},"r":{"f":25,"t":0.5,"l":{"f":29,"t":0.5,"l":{"leaf":0},"r":{"f":42,"t":0.5,"l":{"f":17,"t":0.5,"l":{"leaf":0},"r":{"leaf":0.6}},"r":{"f":23,"t":0.5,"l":{"leaf":0.8983050847457628},"r":{"leaf":0.5}}}},"r":{"leaf":1}}}},{"f":29,"t":0.5,"l":{"leaf":0},"r":{"f":28,"t":1.5,"l":{"f":41,"t":1.5,"l":{"f":36,"t":0.5,"l":{"leaf":0.5},"r":{"leaf":0}},"r":{"leaf":0}},"r":{"f":45,"t":0.6499999999999999,"l":{"f":4,"t":0.5,"l":{"f":41,"t":4.5,"l":{"f":0,"t":0.5,"l":{"leaf":0.5},"r":{"leaf":0.34210526315789475}},"r":{"f":45,"t":0.575,"l":{"leaf":0.92},"r":{"leaf":1}}},"r":{"leaf":0}},"r":{"leaf":1}}}},{"f":4,"t":0.5,"l":{"f":41,"t":4.5,"l":{"f":18,"t":0.5,"l":{"f":13,"t":0.5,"l":{"f":10,"t":38,"l":{"f":3,"t":0.5,"l":{"leaf":0.1875},"r":{"leaf":0}},"r":{"f":17,"t":0.5,"l":{"leaf":0.3333333333333333},"r":{"leaf":0.8461538461538461}}},"r":{"leaf":1}},"r":{"leaf":0}},"r":{"f":29,"t":0.5,"l":{"leaf":0},"r":{"f":41,"t":9.5,"l":{"f":16,"t":0.5,"l":{"f":9,"t":2.5,"l":{"leaf":0.967741935483871},"r":{"leaf":0.6923076923076923}},"r":{"leaf":0}},"r":{"f":9,"t":1,"l":{"leaf":0.9411764705882353},"r":{"leaf":1}}}}},"r":{"leaf":0}},{"f":42,"t":0.5,"l":{"f":11,"t":4.66,"l":{"f":18,"t":0.5,"l":{"f":45,"t":0.7,"l":{"f":10,"t":7,"l":{"f":27,"t":0.5,"l":{"leaf":0},"r":{"leaf":1}},"r":{"f":17,"t":0.5,"l":{"leaf":0},"r":{"leaf":0.05}}},"r":{"f":9,"t":2.5,"l":{"leaf":0.5},"r":{"leaf":1}}},"r":{"leaf":0}},"r":{"f":6,"t":0.5,"l":{"leaf":0.6666666666666666},"r":{"leaf":1}}},"r":{"f":22,"t":0.5,"l":{"f":29,"t":0.5,"l":{"leaf":0},"r":{"f":11,"t":1.7000000000000002,"l":{"leaf":0},"r":{"f":36,"t":0.5,"l":{"f":26,"t":3.5,"l":{"leaf":0.8571428571428571},"r":{"leaf":0.9850746268656716}},"r":{"leaf":0}}}},"r":{"leaf":0}}},{"f":38,"t":0.5,"l":{"f":41,"t":4.5,"l":{"f":27,"t":0.5,"l":{"f":23,"t":0.5,"l":{"leaf":0},"r":{"leaf":0.25}},"r":{"f":5,"t":0.5,"l":{"f":31,"t":0.5,"l":{"leaf":0},"r":{"f":0,"t":0.5,"l":{"leaf":0.7},"r":{"leaf":1}}},"r":{"f":23,"t":0.5,"l":{"f":44,"t":0.5,"l":{"leaf":0.36363636363636365},"r":{"leaf":0}},"r":{"f":12,"t":1,"l":{"leaf":0},"r":{"leaf":0.5}}}}},"r":{"f":30,"t":0.5,"l":{"leaf":0},"r":{"f":10,"t":10.5,"l":{"leaf":1},"r":{"f":36,"t":0.5,"l":{"f":45,"t":0.575,"l":{"leaf":0.5757575757575758},"r":{"leaf":0.8623853211009175}},"r":{"leaf":0}}}}},"r":{"leaf":0}},{"f":26,"t":2.5,"l":{"f":23,"t":0.5,"l":{"leaf":0},"r":{"f":10,"t":36,"l":{"leaf":0},"r":{"leaf":1}}},"r":{"f":3,"t":0.5,"l":{"f":30,"t":0.5,"l":{"leaf":0},"r":{"f":32,"t":0.5,"l":{"f":34,"t":0.5,"l":{"f":22,"t":0.5,"l":{"leaf":0.7574468085106383},"r":{"leaf":0}},"r":{"leaf":0}},"r":{"leaf":0}}},"r":{"leaf":1}}},{"f":45,"t":0.6499999999999999,"l":{"f":27,"t":0.5,"l":{"f":11,"t":4.609999999999999,"l":{"leaf":0},"r":{"leaf":1}},"r":{"f":30,"t":0.5,"l":{"leaf":0},"r":{"f":4,"t":0.5,"l":{"f":31,"t":0.5,"l":{"leaf":0},"r":{"f":25,"t":0.5,"l":{"leaf":0.6418918918918919},"r":{"leaf":1}}},"r":{"leaf":0}}}},"r":{"f":4,"t":0.5,"l":{"f":28,"t":1.5,"l":{"leaf":0},"r":{"f":9,"t":2.5,"l":{"leaf":0.7808219178082192},"r":{"leaf":1}}},"r":{"leaf":0}}},{"f":45,"t":0.375,"l":{"leaf":0},"r":{"f":4,"t":0.5,"l":{"f":26,"t":2.5,"l":{"f":11,"t":4.609999999999999,"l":{"leaf":0},"r":{"leaf":1}},"r":{"f":30,"t":0.5,"l":{"leaf":0},"r":{"f":9,"t":1,"l":{"leaf":1},"r":{"f":45,"t":0.75,"l":{"leaf":0.6605504587155964},"r":{"leaf":1}}}}},"r":{"leaf":0}}},{"f":27,"t":0.5,"l":{"f":6,"t":0.5,"l":{"leaf":0},"r":{"f":17,"t":0.5,"l":{"leaf":0},"r":{"leaf":1}}},"r":{"f":30,"t":0.5,"l":{"leaf":0},"r":{"f":34,"t":0.5,"l":{"f":41,"t":61,"l":{"f":29,"t":0.5,"l":{"leaf":0},"r":{"f":42,"t":0.5,"l":{"leaf":0.574468085106383},"r":{"leaf":0.9315068493150684}}},"r":{"f":12,"t":0.5,"l":{"f":31,"t":0.5,"l":{"leaf":0},"r":{"leaf":0.6111111111111112}},"r":{"leaf":0.5}}},"r":{"leaf":0}}}},{"f":10,"t":38,"l":{"f":29,"t":0.5,"l":{"leaf":0},"r":{"f":27,"t":0.5,"l":{"leaf":0},"r":{"f":41,"t":5.5,"l":{"f":44,"t":0.5,"l":{"f":45,"t":0.7,"l":{"leaf":0.16666666666666666},"r":{"leaf":1}},"r":{"leaf":0}},"r":{"f":41,"t":8.5,"l":{"f":12,"t":0.5,"l":{"leaf":1},"r":{"leaf":0.25}},"r":{"f":16,"t":0.5,"l":{"leaf":0.9699248120300752},"r":{"leaf":0}}}}}},"r":{"f":0,"t":0.5,"l":{"f":12,"t":1.5,"l":{"leaf":0},"r":{"leaf":1}},"r":{"f":18,"t":0.5,"l":{"leaf":0.9473684210526315},"r":{"leaf":1}}}},{"f":26,"t":2.5,"l":{"f":41,"t":1.5,"l":{"f":11,"t":4.0649999999999995,"l":{"leaf":0},"r":{"leaf":1}},"r":{"leaf":0}},"r":{"f":31,"t":0.5,"l":{"leaf":0},"r":{"f":30,"t":0.5,"l":{"leaf":0},"r":{"f":32,"t":0.5,"l":{"f":16,"t":0.5,"l":{"f":26,"t":3.5,"l":{"leaf":0.8428571428571429},"r":{"leaf":0.7472527472527473}},"r":{"leaf":0}},"r":{"leaf":0}}}}},{"f":44,"t":0.5,"l":{"f":4,"t":0.5,"l":{"f":27,"t":0.5,"l":{"leaf":0},"r":{"f":11,"t":2.415,"l":{"f":10,"t":10,"l":{"leaf":1},"r":{"f":11,"t":1.975,"l":{"leaf":0},"r":{"leaf":0.4}}},"r":{"f":30,"t":0.5,"l":{"leaf":0},"r":{"f":32,"t":0.5,"l":{"leaf":0.8205128205128205},"r":{"leaf":0}}}}},"r":{"leaf":0}},"r":{"leaf":0}},{"f":26,"t":2.5,"l":{"f":17,"t":0.5,"l":{"leaf":0},"r":{"f":11,"t":4.09,"l":{"leaf":0},"r":{"leaf":0.5}}},"r":{"f":10,"t":14,"l":{"f":26,"t":3.5,"l":{"f":4,"t":0.5,"l":{"f":44,"t":0.5,"l":{"leaf":1},"r":{"leaf":0}},"r":{"leaf":0}},"r":{"f":29,"t":0.5,"l":{"leaf":0},"r":{"f":31,"t":0.5,"l":{"leaf":0},"r":{"leaf":1}}}},"r":{"f":29,"t":0.5,"l":{"leaf":0},"r":{"f":4,"t":0.5,"l":{"f":41,"t":8.5,"l":{"f":45,"t":0.575,"l":{"leaf":0},"r":{"leaf":0.4883720930232558}},"r":{"leaf":1}},"r":{"leaf":0}}}}},{"f":29,"t":0.5,"l":{"leaf":0},"r":{"f":42,"t":0.5,"l":{"f":11,"t":4.609999999999999,"l":{"f":45,"t":0.7,"l":{"f":11,"t":1.54,"l":{"f":28,"t":1.5,"l":{"leaf":0},"r":{"leaf":1}},"r":{"f":12,"t":1.5,"l":{"leaf":0},"r":{"leaf":0.1111111111111111}}},"r":{"f":28,"t":1.5,"l":{"leaf":0},"r":{"leaf":1}}},"r":{"leaf":0.7368421052631579}},"r":{"f":38,"t":0.5,"l":{"f":28,"t":1,"l":{"leaf":0},"r":{"f":26,"t":3.5,"l":{"f":24,"t":0.5,"l":{"leaf":0.85},"r":{"leaf":1}},"r":{"f":31,"t":0.5,"l":{"leaf":0},"r":{"leaf":0.9929577464788732}}}},"r":{"leaf":0}}}},{"f":29,"t":0.5,"l":{"leaf":0},"r":{"f":42,"t":0.5,"l":{"f":0,"t":0.5,"l":{"f":27,"t":0.5,"l":{"f":40,"t":0.5,"l":{"f":9,"t":1.5,"l":{"leaf":0},"r":{"leaf":0.09090909090909091}},"r":{"leaf":0}},"r":{"f":33,"t":0.5,"l":{"leaf":0.5714285714285714},"r":{"leaf":0}}},"r":{"f":41,"t":1.5,"l":{"f":11,"t":3.9399999999999995,"l":{"leaf":0.2857142857142857},"r":{"f":11,"t":4.955,"l":{"leaf":1},"r":{"leaf":0.5}}},"r":{"f":24,"t":0.5,"l":{"f":36,"t":0.5,"l":{"leaf":0.38461538461538464},"r":{"leaf":0}},"r":{"leaf":0}}}},"r":{"f":22,"t":0.5,"l":{"f":26,"t":2.5,"l":{"leaf":0},"r":{"f":41,"t":8.5,"l":{"f":9,"t":2.5,"l":{"leaf":0.8620689655172413},"r":{"leaf":0.2222222222222222}},"r":{"f":45,"t":0.575,"l":{"leaf":0.9375},"r":{"leaf":1}}}},"r":{"leaf":0}}}},{"f":26,"t":2.5,"l":{"f":12,"t":1.5,"l":{"leaf":0},"r":{"f":23,"t":0.5,"l":{"leaf":0},"r":{"f":36,"t":0.5,"l":{"leaf":1},"r":{"leaf":0}}}},"r":{"f":29,"t":0.5,"l":{"leaf":0},"r":{"f":18,"t":0.5,"l":{"f":10,"t":23,"l":{"f":4,"t":0.5,"l":{"f":41,"t":9.5,"l":{"leaf":0.8235294117647058},"r":{"leaf":0.9921259842519685}},"r":{"leaf":0}},"r":{"f":9,"t":1,"l":{"leaf":1},"r":{"f":10,"t":38,"l":{"leaf":0.23076923076923078},"r":{"leaf":0.8}}}},"r":{"leaf":0.5294117647058824}}}},{"f":16,"t":0.5,"l":{"f":26,"t":2.5,"l":{"f":12,"t":1.5,"l":{"leaf":0},"r":{"f":45,"t":0.4,"l":{"leaf":0},"r":{"leaf":1}}},"r":{"f":10,"t":14,"l":{"f":9,"t":2.5,"l":{"f":11,"t":2.415,"l":{"f":3,"t":0.5,"l":{"leaf":0.5},"r":{"leaf":1}},"r":{"f":25,"t":0.5,"l":{"leaf":0.8904109589041096},"r":{"leaf":1}}},"r":{"f":41,"t":8,"l":{"leaf":0.6666666666666666},"r":{"leaf":1}}},"r":{"f":41,"t":8.5,"l":{"f":11,"t":4.665,"l":{"f":19,"t":1.5,"l":{"leaf":0},"r":{"leaf":0.16}},"r":{"f":42,"t":0.5,"l":{"leaf":0.7},"r":{"leaf":1}}},"r":{"f":10,"t":27,"l":{"f":11,"t":3.185,"l":{"leaf":0.4852941176470588},"r":{"leaf":0.8064516129032258}},"r":{"leaf":1}}}}},"r":{"leaf":0}},{"f":16,"t":0.5,"l":{"f":4,"t":0.5,"l":{"f":32,"t":0.5,"l":{"f":30,"t":0.5,"l":{"leaf":0},"r":{"f":26,"t":2.5,"l":{"leaf":0.07142857142857142},"r":{"f":26,"t":3.5,"l":{"leaf":0.8970588235294118},"r":{"leaf":0.7470588235294118}}}},"r":{"leaf":0}},"r":{"leaf":0}},"r":{"leaf":0}},{"f":28,"t":1.5,"l":{"f":6,"t":0.5,"l":{"leaf":0},"r":{"f":17,"t":0.5,"l":{"leaf":0},"r":{"leaf":1}}},"r":{"f":10,"t":10.5,"l":{"leaf":1},"r":{"f":11,"t":4.79,"l":{"f":32,"t":0.5,"l":{"f":16,"t":0.5,"l":{"f":30,"t":0.5,"l":{"leaf":0},"r":{"leaf":0.610062893081761}},"r":{"leaf":0}},"r":{"leaf":0}},"r":{"f":10,"t":124,"l":{"leaf":1},"r":{"f":34,"t":0.5,"l":{"leaf":1},"r":{"leaf":0}}}}}},{"f":7,"t":0.5,"l":{"f":30,"t":0.5,"l":{"leaf":0},"r":{"f":28,"t":1.5,"l":{"f":9,"t":1.5,"l":{"leaf":0},"r":{"leaf":0.1}},"r":{"f":29,"t":0.5,"l":{"leaf":0},"r":{"f":10,"t":23,"l":{"f":4,"t":0.5,"l":{"leaf":0.912751677852349},"r":{"leaf":0}},"r":{"f":18,"t":0.5,"l":{"leaf":0.5},"r":{"leaf":0}}}}}},"r":{"f":41,"t":1.5,"l":{"leaf":0.5},"r":{"leaf":1}}},{"f":30,"t":0.5,"l":{"leaf":0},"r":{"f":27,"t":0.5,"l":{"f":11,"t":4.449999999999999,"l":{"leaf":0},"r":{"leaf":1}},"r":{"f":41,"t":4.5,"l":{"f":32,"t":0.5,"l":{"f":44,"t":0.5,"l":{"f":34,"t":0.5,"l":{"leaf":0.8275862068965517},"r":{"leaf":0}},"r":{"leaf":0}},"r":{"leaf":0}},"r":{"f":4,"t":0.5,"l":{"f":25,"t":0.5,"l":{"f":23,"t":0.5,"l":{"leaf":0.8415300546448088},"r":{"leaf":1}},"r":{"leaf":1}},"r":{"leaf":0}}}}},{"f":26,"t":2.5,"l":{"leaf":0},"r":{"f":4,"t":0.5,"l":{"f":31,"t":0.5,"l":{"leaf":0},"r":{"f":41,"t":4.5,"l":{"f":10,"t":22,"l":{"f":44,"t":0.5,"l":{"leaf":1},"r":{"leaf":0}},"r":{"f":41,"t":3.5,"l":{"leaf":0.5},"r":{"leaf":0}}},"r":{"f":11,"t":3.205,"l":{"f":10,"t":14,"l":{"leaf":0.8703703703703703},"r":{"leaf":0.35}},"r":{"f":45,"t":0.6499999999999999,"l":{"leaf":1},"r":{"leaf":0.896551724137931}}}}},"r":{"leaf":0}}},{"f":30,"t":0.5,"l":{"leaf":0},"r":{"f":36,"t":0.5,"l":{"f":26,"t":2.5,"l":{"leaf":0},"r":{"f":29,"t":0.5,"l":{"leaf":0},"r":{"f":42,"t":0.5,"l":{"f":34,"t":0.5,"l":{"leaf":0.5},"r":{"leaf":0}},"r":{"f":17,"t":0.5,"l":{"leaf":0.943502824858757},"r":{"leaf":1}}}}},"r":{"leaf":0}}},{"f":5,"t":0.5,"l":{"f":29,"t":0.5,"l":{"leaf":0},"r":{"f":28,"t":1.5,"l":{"f":9,"t":1.5,"l":{"leaf":0},"r":{"leaf":0.5}},"r":{"f":23,"t":0.5,"l":{"leaf":0.9395604395604396},"r":{"leaf":1}}}},"r":{"f":41,"t":1.5,"l":{"f":34,"t":0.5,"l":{"leaf":1},"r":{"leaf":0}},"r":{"f":0,"t":0.5,"l":{"leaf":0},"r":{"f":17,"t":0.5,"l":{"f":44,"t":0.5,"l":{"f":11,"t":4.54,"l":{"leaf":0},"r":{"leaf":1}},"r":{"leaf":0}},"r":{"leaf":0.375}}}}},{"f":26,"t":2.5,"l":{"f":11,"t":4.34,"l":{"leaf":0},"r":{"leaf":0.5}},"r":{"f":29,"t":0.5,"l":{"leaf":0},"r":{"f":5,"t":0.5,"l":{"leaf":0.9069767441860465},"r":{"f":11,"t":4.445,"l":{"leaf":0},"r":{"leaf":0.6551724137931034}}}}},{"f":26,"t":2.5,"l":{"leaf":0},"r":{"f":29,"t":0.5,"l":{"leaf":0},"r":{"f":16,"t":0.5,"l":{"f":34,"t":0.5,"l":{"f":32,"t":0.5,"l":{"f":9,"t":1,"l":{"leaf":1},"r":{"leaf":0.92}},"r":{"leaf":0}},"r":{"leaf":0}},"r":{"leaf":0}}}},{"f":38,"t":0.5,"l":{"f":28,"t":1.5,"l":{"f":10,"t":36,"l":{"leaf":0},"r":{"leaf":1}},"r":{"f":10,"t":14,"l":{"f":29,"t":0.5,"l":{"leaf":0},"r":{"f":32,"t":0.5,"l":{"f":31,"t":0.5,"l":{"leaf":0},"r":{"leaf":0.9915254237288136}},"r":{"leaf":0}}},"r":{"f":25,"t":0.5,"l":{"f":32,"t":0.5,"l":{"f":12,"t":1.5,"l":{"leaf":0.3157894736842105},"r":{"leaf":0.8461538461538461}},"r":{"leaf":0}},"r":{"leaf":1}}}},"r":{"leaf":0}},{"f":29,"t":0.5,"l":{"leaf":0},"r":{"f":27,"t":0.5,"l":{"f":41,"t":1.5,"l":{"f":25,"t":0.5,"l":{"leaf":0.75},"r":{"leaf":0}},"r":{"leaf":0}},"r":{"f":32,"t":0.5,"l":{"f":31,"t":0.5,"l":{"leaf":0},"r":{"f":33,"t":0.5,"l":{"f":16,"t":0.5,"l":{"leaf":0.9222797927461139},"r":{"leaf":0}},"r":{"leaf":0}}},"r":{"leaf":0}}}},{"f":29,"t":0.5,"l":{"leaf":0},"r":{"f":32,"t":0.5,"l":{"f":27,"t":0.5,"l":{"f":10,"t":36,"l":{"leaf":0},"r":{"leaf":1}},"r":{"f":24,"t":0.5,"l":{"f":26,"t":3.5,"l":{"f":16,"t":0.5,"l":{"leaf":0.8611111111111112},"r":{"leaf":0}},"r":{"f":10,"t":27.5,"l":{"leaf":0.9708029197080292},"r":{"leaf":0}}},"r":{"f":3,"t":0.5,"l":{"leaf":0.8333333333333334},"r":{"leaf":1}}}},"r":{"leaf":0}}},{"f":26,"t":2.5,"l":{"f":11,"t":4.609999999999999,"l":{"leaf":0},"r":{"leaf":1}},"r":{"f":9,"t":1,"l":{"leaf":1},"r":{"f":29,"t":0.5,"l":{"leaf":0},"r":{"f":16,"t":0.5,"l":{"f":23,"t":0.5,"l":{"f":5,"t":0.5,"l":{"leaf":0.8988095238095238},"r":{"leaf":0.36363636363636365}},"r":{"f":11,"t":5.66,"l":{"leaf":0.125},"r":{"leaf":1}}},"r":{"leaf":0}}}}},{"f":41,"t":5.5,"l":{"f":4,"t":0.5,"l":{"f":9,"t":1,"l":{"f":24,"t":0.5,"l":{"leaf":0},"r":{"leaf":1}},"r":{"f":24,"t":0.5,"l":{"f":45,"t":0.575,"l":{"leaf":1},"r":{"f":12,"t":1.5,"l":{"leaf":0.13043478260869565},"r":{"leaf":0.8421052631578947}}},"r":{"leaf":0}}},"r":{"leaf":0}},"r":{"f":30,"t":0.5,"l":{"leaf":0},"r":{"f":28,"t":1.5,"l":{"leaf":0},"r":{"f":12,"t":0.5,"l":{"f":29,"t":0.5,"l":{"leaf":0},"r":{"f":10,"t":14,"l":{"leaf":1},"r":{"leaf":0.9285714285714286}}},"r":{"f":10,"t":14,"l":{"f":9,"t":2.5,"l":{"leaf":0.8823529411764706},"r":{"leaf":1}},"r":{"f":16,"t":0.5,"l":{"leaf":0.7037037037037037},"r":{"leaf":0}}}}}}},{"f":41,"t":8.5,"l":{"f":25,"t":0.5,"l":{"f":34,"t":0.5,"l":{"f":11,"t":4.665,"l":{"f":5,"t":0.5,"l":{"f":10,"t":14,"l":{"leaf":0.8695652173913043},"r":{"leaf":0}},"r":{"f":45,"t":0.575,"l":{"leaf":0},"r":{"leaf":0.05263157894736842}}},"r":{"leaf":0.9444444444444444}},"r":{"leaf":0}},"r":{"leaf":0}},"r":{"f":29,"t":0.5,"l":{"leaf":0},"r":{"f":4,"t":0.5,"l":{"f":31,"t":0.5,"l":{"leaf":0},"r":{"f":41,"t":48,"l":{"leaf":1},"r":{"f":7,"t":0.5,"l":{"leaf":0.9710144927536232},"r":{"leaf":1}}}},"r":{"leaf":0}}}},{"f":26,"t":2.5,"l":{"f":5,"t":0.5,"l":{"f":10,"t":34,"l":{"leaf":0},"r":{"leaf":1}},"r":{"leaf":0}},"r":{"f":10,"t":14,"l":{"f":29,"t":0.5,"l":{"leaf":0},"r":{"f":44,"t":0.5,"l":{"f":41,"t":43.5,"l":{"leaf":1},"r":{"f":12,"t":0.5,"l":{"leaf":0.9555555555555556},"r":{"leaf":0.6}}},"r":{"leaf":0}}},"r":{"f":3,"t":0.5,"l":{"f":10,"t":44,"l":{"f":30,"t":0.5,"l":{"leaf":0},"r":{"f":9,"t":2.5,"l":{"leaf":0.6779661016949152},"r":{"leaf":0.225}}},"r":{"f":41,"t":2,"l":{"f":17,"t":0.5,"l":{"leaf":1},"r":{"leaf":0}},"r":{"leaf":1}}},"r":{"leaf":1}}}},{"f":27,"t":0.5,"l":{"f":41,"t":1.5,"l":{"f":6,"t":0.5,"l":{"leaf":0},"r":{"leaf":0.6666666666666666}},"r":{"leaf":0}},"r":{"f":29,"t":0.5,"l":{"leaf":0},"r":{"f":42,"t":0.5,"l":{"f":31,"t":0.5,"l":{"leaf":0},"r":{"f":10,"t":22,"l":{"f":5,"t":0.5,"l":{"leaf":1},"r":{"leaf":0.5}},"r":{"f":33,"t":0.5,"l":{"leaf":0.45161290322580644},"r":{"leaf":0}}}},"r":{"f":4,"t":0.5,"l":{"f":11,"t":2.975,"l":{"leaf":1},"r":{"f":5,"t":0.5,"l":{"leaf":0.9107142857142857},"r":{"leaf":0.6363636363636364}}},"r":{"leaf":0}}}}},{"f":26,"t":2.5,"l":{"f":41,"t":1.5,"l":{"f":28,"t":0.5,"l":{"leaf":0},"r":{"leaf":1}},"r":{"leaf":0}},"r":{"f":29,"t":0.5,"l":{"leaf":0},"r":{"f":36,"t":0.5,"l":{"f":33,"t":0.5,"l":{"f":41,"t":8.5,"l":{"f":24,"t":0.5,"l":{"leaf":0.6470588235294118},"r":{"leaf":0.4444444444444444}},"r":{"f":11,"t":2.725,"l":{"leaf":1},"r":{"leaf":0.9583333333333334}}},"r":{"leaf":0}},"r":{"leaf":0}}}},{"f":4,"t":0.5,"l":{"f":26,"t":2.5,"l":{"leaf":0},"r":{"f":31,"t":0.5,"l":{"leaf":0},"r":{"f":29,"t":0.5,"l":{"leaf":0},"r":{"f":34,"t":0.5,"l":{"f":41,"t":4.5,"l":{"leaf":0.6538461538461539},"r":{"leaf":0.9776536312849162}},"r":{"leaf":0}}}}},"r":{"leaf":0}},{"f":27,"t":0.5,"l":{"f":12,"t":1.5,"l":{"leaf":0},"r":{"f":3,"t":0.5,"l":{"f":9,"t":1.5,"l":{"leaf":0},"r":{"leaf":1}},"r":{"leaf":0}}},"r":{"f":36,"t":0.5,"l":{"f":30,"t":0.5,"l":{"leaf":0},"r":{"f":29,"t":0.5,"l":{"leaf":0},"r":{"f":41,"t":8.5,"l":{"f":24,"t":0.5,"l":{"leaf":0.6388888888888888},"r":{"leaf":0.2727272727272727}},"r":{"f":41,"t":61,"l":{"leaf":1},"r":{"leaf":0.8108108108108109}}}}},"r":{"leaf":0}}},{"f":26,"t":2.5,"l":{"f":23,"t":0.5,"l":{"leaf":0},"r":{"f":12,"t":1.5,"l":{"leaf":0},"r":{"leaf":1}}},"r":{"f":11,"t":4.645,"l":{"f":45,"t":0.75,"l":{"f":29,"t":0.5,"l":{"leaf":0},"r":{"f":41,"t":5.5,"l":{"f":9,"t":2.5,"l":{"leaf":0.5454545454545454},"r":{"leaf":0}},"r":{"f":25,"t":0.5,"l":{"leaf":0.8828828828828829},"r":{"leaf":1}}}},"r":{"leaf":1}},"r":{"f":3,"t":0.5,"l":{"leaf":0.9090909090909091},"r":{"leaf":1}}}},{"f":28,"t":1.5,"l":{"f":45,"t":0.575,"l":{"leaf":0},"r":{"f":41,"t":1.5,"l":{"leaf":1},"r":{"leaf":0}}},"r":{"f":29,"t":0.5,"l":{"leaf":0},"r":{"f":41,"t":4.5,"l":{"f":18,"t":0.5,"l":{"f":44,"t":0.5,"l":{"f":24,"t":0.5,"l":{"leaf":0.6571428571428571},"r":{"leaf":0}},"r":{"leaf":0}},"r":{"leaf":0}},"r":{"f":13,"t":0.5,"l":{"f":41,"t":8.5,"l":{"f":3,"t":0.5,"l":{"leaf":0.8636363636363636},"r":{"leaf":1}},"r":{"f":41,"t":48,"l":{"leaf":1},"r":{"leaf":0.9701492537313433}}},"r":{"leaf":0.3333333333333333}}}}},{"f":36,"t":0.5,"l":{"f":41,"t":4.5,"l":{"f":9,"t":1.5,"l":{"leaf":0},"r":{"f":10,"t":38,"l":{"f":5,"t":0.5,"l":{"leaf":0.42857142857142855},"r":{"f":28,"t":1.5,"l":{"leaf":0},"r":{"leaf":0.09090909090909091}}},"r":{"leaf":0.7777777777777778}}},"r":{"f":12,"t":1.5,"l":{"f":28,"t":1.5,"l":{"leaf":0},"r":{"f":30,"t":0.5,"l":{"leaf":0},"r":{"leaf":0.7614213197969543}}},"r":{"leaf":1}}},"r":{"leaf":0}},{"f":26,"t":2.5,"l":{"leaf":0},"r":{"f":45,"t":0.75,"l":{"f":30,"t":0.5,"l":{"leaf":0},"r":{"f":31,"t":0.5,"l":{"leaf":0},"r":{"f":4,"t":0.5,"l":{"f":45,"t":0.6499999999999999,"l":{"leaf":0.75625},"r":{"leaf":0.47761194029850745}},"r":{"leaf":0}}}},"r":{"leaf":1}}},{"f":2,"t":0.5,"l":{"f":26,"t":2.5,"l":{"f":10,"t":31.5,"l":{"leaf":0},"r":{"leaf":0.25}},"r":{"f":41,"t":4.5,"l":{"f":11,"t":4.665,"l":{"f":24,"t":0.5,"l":{"f":12,"t":0.5,"l":{"leaf":0.7142857142857143},"r":{"leaf":0.21739130434782608}},"r":{"leaf":0}},"r":{"leaf":0.8235294117647058}},"r":{"f":16,"t":0.5,"l":{"f":44,"t":0.5,"l":{"f":41,"t":30.5,"l":{"leaf":0.918918918918919},"r":{"leaf":0.68}},"r":{"leaf":0}},"r":{"leaf":0}}}},"r":{"leaf":0}},{"f":26,"t":2.5,"l":{"f":41,"t":1.5,"l":{"f":10,"t":29,"l":{"leaf":0},"r":{"leaf":1}},"r":{"leaf":0}},"r":{"f":34,"t":0.5,"l":{"f":25,"t":0.5,"l":{"f":42,"t":0.5,"l":{"f":11,"t":4.67,"l":{"f":11,"t":3.175,"l":{"leaf":0.7647058823529411},"r":{"leaf":0.06666666666666667}},"r":{"leaf":1}},"r":{"f":30,"t":0.5,"l":{"leaf":0},"r":{"f":41,"t":30.5,"l":{"leaf":0.9047619047619048},"r":{"leaf":0.6141732283464567}}}},"r":{"leaf":1}},"r":{"leaf":0}}},{"f":29,"t":0.5,"l":{"leaf":0},"r":{"f":11,"t":2.02,"l":{"f":9,"t":1.5,"l":{"leaf":0},"r":{"f":5,"t":0.5,"l":{"f":27,"t":0.5,"l":{"leaf":0},"r":{"leaf":1}},"r":{"leaf":0}}},"r":{"f":45,"t":0.375,"l":{"leaf":0},"r":{"f":22,"t":0.5,"l":{"f":32,"t":0.5,"l":{"f":42,"t":0.5,"l":{"leaf":0.6923076923076923},"r":{"leaf":0.9411764705882353}},"r":{"leaf":0}},"r":{"leaf":0}}}}},{"f":29,"t":0.5,"l":{"leaf":0},"r":{"f":26,"t":3.5,"l":{"f":11,"t":4.52,"l":{"f":7,"t":0.5,"l":{"f":9,"t":2.5,"l":{"leaf":0},"r":{"f":10,"t":18,"l":{"leaf":0},"r":{"leaf":0.23529411764705882}}},"r":{"f":44,"t":0.5,"l":{"leaf":1},"r":{"leaf":0}}},"r":{"f":32,"t":0.5,"l":{"leaf":1},"r":{"leaf":0}}},"r":{"f":24,"t":0.5,"l":{"f":10,"t":27.5,"l":{"f":11,"t":2.975,"l":{"leaf":0.9896907216494846},"r":{"f":45,"t":0.575,"l":{"leaf":0.8},"r":{"leaf":1}}},"r":{"leaf":0}},"r":{"leaf":1}}}},{"f":27,"t":0.5,"l":{"f":23,"t":0.5,"l":{"leaf":0},"r":{"f":22,"t":0.5,"l":{"leaf":0.8},"r":{"leaf":0}}},"r":{"f":29,"t":0.5,"l":{"leaf":0},"r":{"f":32,"t":0.5,"l":{"f":12,"t":0.5,"l":{"f":36,"t":0.5,"l":{"f":11,"t":2.9050000000000002,"l":{"leaf":0.9893617021276596},"r":{"leaf":0.9166666666666666}},"r":{"leaf":0}},"r":{"f":16,"t":0.5,"l":{"f":7,"t":0.5,"l":{"leaf":0.7532467532467533},"r":{"leaf":0.9545454545454546}},"r":{"leaf":0}}},"r":{"leaf":0}}}},{"f":32,"t":0.5,"l":{"f":4,"t":0.5,"l":{"f":29,"t":0.5,"l":{"leaf":0},"r":{"f":31,"t":0.5,"l":{"leaf":0},"r":{"f":5,"t":0.5,"l":{"f":28,"t":0.5,"l":{"leaf":0},"r":{"leaf":0.9375}},"r":{"f":11,"t":3.5,"l":{"leaf":0},"r":{"leaf":0.9285714285714286}}}}},"r":{"leaf":0}},"r":{"leaf":0}},{"f":42,"t":0.5,"l":{"f":25,"t":0.5,"l":{"f":23,"t":0.5,"l":{"f":2,"t":0.5,"l":{"f":10,"t":44,"l":{"f":12,"t":0.5,"l":{"leaf":0.36363636363636365},"r":{"leaf":0.10714285714285714}},"r":{"leaf":1}},"r":{"leaf":0}},"r":{"f":11,"t":4.085,"l":{"leaf":0},"r":{"f":10,"t":82.5,"l":{"leaf":1},"r":{"leaf":0.4}}}},"r":{"leaf":0}},"r":{"f":28,"t":1.5,"l":{"leaf":0},"r":{"f":30,"t":0.5,"l":{"leaf":0},"r":{"f":11,"t":2.415,"l":{"f":29,"t":0.5,"l":{"leaf":0},"r":{"leaf":0.8888888888888888}},"r":{"f":29,"t":0.5,"l":{"leaf":0},"r":{"f":22,"t":0.5,"l":{"leaf":0.9192546583850931},"r":{"leaf":0}}}}}}},{"f":27,"t":0.5,"l":{"f":9,"t":1.5,"l":{"leaf":0},"r":{"f":5,"t":0.5,"l":{"leaf":0.16666666666666666},"r":{"leaf":0}}},"r":{"f":44,"t":0.5,"l":{"f":7,"t":0.5,"l":{"f":32,"t":0.5,"l":{"f":29,"t":0.5,"l":{"leaf":0},"r":{"f":9,"t":2.5,"l":{"leaf":0.9230769230769231},"r":{"leaf":0.5384615384615384}}},"r":{"leaf":0}},"r":{"leaf":1}},"r":{"leaf":0}}},{"f":29,"t":0.5,"l":{"leaf":0},"r":{"f":4,"t":0.5,"l":{"f":31,"t":0.5,"l":{"leaf":0},"r":{"f":28,"t":1.5,"l":{"f":3,"t":0.5,"l":{"f":8,"t":0.5,"l":{"leaf":0.375},"r":{"leaf":0}},"r":{"leaf":0}},"r":{"f":34,"t":0.5,"l":{"f":5,"t":0.5,"l":{"leaf":0.9761904761904762},"r":{"leaf":0.6666666666666666}},"r":{"leaf":0}}}},"r":{"leaf":0}}},{"f":41,"t":5.5,"l":{"f":12,"t":1.5,"l":{"f":11,"t":3.605,"l":{"f":45,"t":0.7,"l":{"f":41,"t":4.5,"l":{"f":45,"t":0.575,"l":{"leaf":0.42857142857142855},"r":{"leaf":0}},"r":{"leaf":1}},"r":{"f":27,"t":0.5,"l":{"leaf":0},"r":{"leaf":1}}},"r":{"leaf":0}},"r":{"f":45,"t":0.4,"l":{"leaf":0},"r":{"f":10,"t":38.5,"l":{"leaf":0.3333333333333333},"r":{"f":17,"t":0.5,"l":{"leaf":1},"r":{"f":10,"t":86.5,"l":{"leaf":1},"r":{"leaf":0.3333333333333333}}}}}},"r":{"f":5,"t":0.5,"l":{"f":28,"t":1,"l":{"leaf":0},"r":{"f":10,"t":10.5,"l":{"leaf":1},"r":{"f":45,"t":0.75,"l":{"f":30,"t":0.5,"l":{"leaf":0},"r":{"leaf":0.7379310344827587}},"r":{"leaf":1}}}},"r":{"f":27,"t":0.5,"l":{"leaf":0},"r":{"f":45,"t":0.575,"l":{"leaf":0},"r":{"f":19,"t":1.5,"l":{"leaf":1},"r":{"f":24,"t":0.5,"l":{"leaf":0},"r":{"leaf":1}}}}}}},{"f":29,"t":0.5,"l":{"leaf":0},"r":{"f":26,"t":2.5,"l":{"f":11,"t":4.449999999999999,"l":{"leaf":0},"r":{"leaf":1}},"r":{"f":11,"t":1.945,"l":{"f":10,"t":20,"l":{"leaf":0.25},"r":{"leaf":0}},"r":{"f":32,"t":0.5,"l":{"f":31,"t":0.5,"l":{"leaf":0},"r":{"f":12,"t":0.5,"l":{"leaf":0.9819819819819819},"r":{"leaf":0.8260869565217391}}},"r":{"leaf":0}}}}},{"f":29,"t":0.5,"l":{"leaf":0},"r":{"f":44,"t":0.5,"l":{"f":42,"t":0.5,"l":{"f":11,"t":4,"l":{"f":27,"t":0.5,"l":{"leaf":0},"r":{"f":33,"t":0.5,"l":{"leaf":0.5294117647058824},"r":{"leaf":0}}},"r":{"f":9,"t":1.5,"l":{"leaf":0},"r":{"f":24,"t":0.5,"l":{"leaf":0.7894736842105263},"r":{"leaf":0}}}},"r":{"f":7,"t":0.5,"l":{"f":28,"t":1.5,"l":{"leaf":0},"r":{"f":12,"t":0.5,"l":{"leaf":0.9615384615384616},"r":{"leaf":0.75}}},"r":{"leaf":1}}},"r":{"leaf":0}}},{"f":29,"t":0.5,"l":{"leaf":0},"r":{"f":31,"t":0.5,"l":{"leaf":0},"r":{"f":4,"t":0.5,"l":{"f":16,"t":0.5,"l":{"f":28,"t":1.5,"l":{"leaf":0.0625},"r":{"f":42,"t":0.5,"l":{"leaf":0.5},"r":{"leaf":0.949238578680203}}},"r":{"leaf":0}},"r":{"leaf":0}}}},{"f":10,"t":14,"l":{"f":27,"t":0.5,"l":{"leaf":0},"r":{"f":5,"t":0.5,"l":{"f":11,"t":2.415,"l":{"f":3,"t":0.5,"l":{"f":11,"t":2.39,"l":{"leaf":0.8461538461538461},"r":{"leaf":0}},"r":{"leaf":1}},"r":{"leaf":0.9074074074074074}},"r":{"leaf":0}}},"r":{"f":30,"t":0.5,"l":{"leaf":0},"r":{"f":36,"t":0.5,"l":{"f":41,"t":48,"l":{"f":12,"t":1.5,"l":{"f":41,"t":26,"l":{"leaf":0},"r":{"leaf":0.38461538461538464}},"r":{"f":32,"t":0.5,"l":{"leaf":0.8444444444444444},"r":{"leaf":0}}},"r":{"leaf":1}},"r":{"leaf":0}}}},{"f":5,"t":0.5,"l":{"f":27,"t":0.5,"l":{"leaf":0},"r":{"f":29,"t":0.5,"l":{"leaf":0},"r":{"f":42,"t":0.5,"l":{"leaf":0.4444444444444444},"r":{"f":11,"t":2.725,"l":{"leaf":1},"r":{"f":25,"t":0.5,"l":{"leaf":0.9519230769230769},"r":{"leaf":1}}}}}},"r":{"f":38,"t":0.5,"l":{"f":0,"t":0.5,"l":{"leaf":0},"r":{"f":36,"t":0.5,"l":{"f":34,"t":0.5,"l":{"f":12,"t":1.5,"l":{"leaf":0.1111111111111111},"r":{"leaf":0.9523809523809523}},"r":{"leaf":0}},"r":{"leaf":0}}},"r":{"leaf":0}}},{"f":29,"t":0.5,"l":{"leaf":0},"r":{"f":36,"t":0.5,"l":{"f":4,"t":0.5,"l":{"f":41,"t":4.5,"l":{"f":32,"t":0.5,"l":{"f":27,"t":0.5,"l":{"leaf":0.17647058823529413},"r":{"leaf":0.631578947368421}},"r":{"leaf":0}},"r":{"f":41,"t":8.5,"l":{"f":5,"t":0.5,"l":{"leaf":0.9230769230769231},"r":{"leaf":0.25}},"r":{"f":45,"t":0.575,"l":{"leaf":0.9534883720930233},"r":{"leaf":1}}}},"r":{"leaf":0}},"r":{"leaf":0}}},{"f":30,"t":0.5,"l":{"leaf":0},"r":{"f":41,"t":4.5,"l":{"f":28,"t":1.5,"l":{"f":6,"t":0.5,"l":{"leaf":0},"r":{"leaf":0.4}},"r":{"f":31,"t":0.5,"l":{"leaf":0},"r":{"f":34,"t":0.5,"l":{"f":16,"t":0.5,"l":{"leaf":0.6216216216216216},"r":{"leaf":0}},"r":{"leaf":0}}}},"r":{"f":10,"t":10.5,"l":{"leaf":1},"r":{"f":36,"t":0.5,"l":{"f":9,"t":2.5,"l":{"f":27,"t":0.5,"l":{"leaf":0},"r":{"leaf":0.6277372262773723}},"r":{"f":41,"t":8.5,"l":{"leaf":0.25},"r":{"leaf":1}}},"r":{"leaf":0}}}}},{"f":29,"t":0.5,"l":{"leaf":0},"r":{"f":5,"t":0.5,"l":{"f":27,"t":0.5,"l":{"f":41,"t":1.5,"l":{"leaf":0.5},"r":{"leaf":0}},"r":{"f":42,"t":0.5,"l":{"leaf":0.47058823529411764},"r":{"f":9,"t":1,"l":{"leaf":1},"r":{"leaf":0.9315068493150684}}}},"r":{"f":38,"t":0.5,"l":{"f":11,"t":4.505,"l":{"f":10,"t":19,"l":{"leaf":0},"r":{"f":4,"t":0.5,"l":{"leaf":0.42857142857142855},"r":{"leaf":0}}},"r":{"f":10,"t":86.5,"l":{"f":10,"t":36,"l":{"leaf":0.8},"r":{"leaf":1}},"r":{"f":42,"t":0.5,"l":{"leaf":0.4},"r":{"leaf":1}}}},"r":{"leaf":0}}}},{"f":29,"t":0.5,"l":{"leaf":0},"r":{"f":27,"t":0.5,"l":{"f":10,"t":29.5,"l":{"leaf":0},"r":{"leaf":0.3333333333333333}},"r":{"f":11,"t":3.5700000000000003,"l":{"f":5,"t":0.5,"l":{"f":11,"t":2.9050000000000002,"l":{"leaf":0.978021978021978},"r":{"f":7,"t":0.5,"l":{"leaf":0.8852459016393442},"r":{"leaf":1}}},"r":{"leaf":0}},"r":{"f":11,"t":4.529999999999999,"l":{"f":5,"t":0.5,"l":{"leaf":0},"r":{"f":4,"t":0.5,"l":{"leaf":0.125},"r":{"leaf":0}}},"r":{"f":10,"t":36,"l":{"f":41,"t":6.5,"l":{"leaf":0},"r":{"leaf":1}},"r":{"leaf":0.875}}}}}},{"f":28,"t":1.5,"l":{"f":10,"t":36,"l":{"leaf":0},"r":{"leaf":1}},"r":{"f":30,"t":0.5,"l":{"leaf":0},"r":{"f":32,"t":0.5,"l":{"f":41,"t":5.5,"l":{"f":16,"t":0.5,"l":{"f":9,"t":1,"l":{"leaf":1},"r":{"leaf":0.5555555555555556}},"r":{"leaf":0}},"r":{"f":10,"t":10.5,"l":{"leaf":1},"r":{"f":41,"t":8.5,"l":{"leaf":0},"r":{"leaf":0.7696969696969697}}}},"r":{"leaf":0}}}},{"f":26,"t":2.5,"l":{"f":5,"t":0.5,"l":{"f":28,"t":0.5,"l":{"leaf":0},"r":{"f":17,"t":0.5,"l":{"leaf":0},"r":{"leaf":1}}},"r":{"leaf":0}},"r":{"f":32,"t":0.5,"l":{"f":36,"t":0.5,"l":{"f":35,"t":0.5,"l":{"f":29,"t":0.5,"l":{"leaf":0},"r":{"f":41,"t":8.5,"l":{"leaf":0.6111111111111112},"r":{"leaf":0.9705882352941176}}},"r":{"leaf":0}},"r":{"leaf":0}},"r":{"leaf":0}}},{"f":34,"t":0.5,"l":{"f":36,"t":0.5,"l":{"f":28,"t":1.5,"l":{"leaf":0},"r":{"f":33,"t":0.5,"l":{"f":9,"t":1,"l":{"leaf":1},"r":{"f":35,"t":0.5,"l":{"leaf":0.6896551724137931},"r":{"leaf":0}}},"r":{"leaf":0}}},"r":{"leaf":0}},"r":{"leaf":0}},{"f":36,"t":0.5,"l":{"f":38,"t":0.5,"l":{"f":32,"t":0.5,"l":{"f":30,"t":0.5,"l":{"leaf":0},"r":{"f":8,"t":0.5,"l":{"f":10,"t":10.5,"l":{"leaf":0.96},"r":{"leaf":0.7377777777777778}},"r":{"leaf":0}}},"r":{"leaf":0}},"r":{"leaf":0}},"r":{"leaf":0}},{"f":26,"t":2.5,"l":{"f":11,"t":4.609999999999999,"l":{"leaf":0},"r":{"leaf":1}},"r":{"f":44,"t":0.5,"l":{"f":3,"t":0.5,"l":{"f":5,"t":0.5,"l":{"f":33,"t":0.5,"l":{"f":41,"t":30.5,"l":{"leaf":0.9382716049382716},"r":{"leaf":0.5131578947368421}},"r":{"leaf":0}},"r":{"f":11,"t":4.445,"l":{"f":11,"t":4,"l":{"leaf":0},"r":{"leaf":0.4}},"r":{"f":34,"t":0.5,"l":{"leaf":0.9411764705882353},"r":{"leaf":0}}}},"r":{"leaf":1}},"r":{"leaf":0}}},{"f":26,"t":2.5,"l":{"f":12,"t":1.5,"l":{"leaf":0},"r":{"leaf":0.25}},"r":{"f":10,"t":10.5,"l":{"leaf":1},"r":{"f":31,"t":0.5,"l":{"leaf":0},"r":{"f":9,"t":1,"l":{"leaf":1},"r":{"f":29,"t":0.5,"l":{"leaf":0},"r":{"f":26,"t":3.5,"l":{"leaf":0.6962025316455697},"r":{"leaf":0.9560439560439561}}}}}}},{"f":27,"t":0.5,"l":{"leaf":0},"r":{"f":32,"t":0.5,"l":{"f":44,"t":0.5,"l":{"f":9,"t":1,"l":{"leaf":1},"r":{"f":45,"t":0.75,"l":{"f":30,"t":0.5,"l":{"leaf":0},"r":{"leaf":0.6051282051282051}},"r":{"leaf":1}}},"r":{"leaf":0}},"r":{"leaf":0}}},{"f":4,"t":0.5,"l":{"f":31,"t":0.5,"l":{"leaf":0},"r":{"f":30,"t":0.5,"l":{"leaf":0},"r":{"f":34,"t":0.5,"l":{"f":29,"t":0.5,"l":{"leaf":0},"r":{"f":36,"t":0.5,"l":{"leaf":0.8689320388349514},"r":{"leaf":0}}},"r":{"leaf":0}}}},"r":{"leaf":0}},{"f":29,"t":0.5,"l":{"leaf":0},"r":{"f":26,"t":2.5,"l":{"f":11,"t":4.609999999999999,"l":{"leaf":0},"r":{"leaf":1}},"r":{"f":9,"t":2.5,"l":{"f":42,"t":0.5,"l":{"leaf":0.4166666666666667},"r":{"leaf":0.9606299212598425}},"r":{"f":11,"t":4.595000000000001,"l":{"f":41,"t":8.5,"l":{"f":32,"t":0.5,"l":{"leaf":0.21428571428571427},"r":{"leaf":0}},"r":{"f":4,"t":0.5,"l":{"leaf":1},"r":{"leaf":0}}},"r":{"f":11,"t":5.3149999999999995,"l":{"f":24,"t":0.5,"l":{"leaf":1},"r":{"leaf":0.4}},"r":{"leaf":0.3333333333333333}}}}}},{"f":4,"t":0.5,"l":{"f":42,"t":0.5,"l":{"f":9,"t":2.5,"l":{"f":28,"t":1.5,"l":{"f":9,"t":1,"l":{"leaf":0},"r":{"f":41,"t":1.5,"l":{"leaf":0.5},"r":{"leaf":0}}},"r":{"f":31,"t":0.5,"l":{"leaf":0},"r":{"f":33,"t":0.5,"l":{"leaf":1},"r":{"leaf":0}}}},"r":{"leaf":0.47619047619047616}},"r":{"f":36,"t":0.5,"l":{"f":29,"t":0.5,"l":{"leaf":0},"r":{"f":41,"t":8.5,"l":{"f":41,"t":7,"l":{"leaf":1},"r":{"leaf":0}},"r":{"f":41,"t":61,"l":{"leaf":1},"r":{"leaf":0.9583333333333334}}}},"r":{"leaf":0}}},"r":{"leaf":0}},{"f":5,"t":0.5,"l":{"f":26,"t":2.5,"l":{"f":9,"t":1.5,"l":{"leaf":0},"r":{"leaf":0.5}},"r":{"f":29,"t":0.5,"l":{"leaf":0},"r":{"f":42,"t":0.5,"l":{"f":12,"t":0.5,"l":{"leaf":1},"r":{"leaf":0}},"r":{"f":41,"t":9,"l":{"f":25,"t":0.5,"l":{"leaf":0.9230769230769231},"r":{"leaf":1}},"r":{"leaf":1}}}}},"r":{"f":4,"t":0.5,"l":{"f":9,"t":2.5,"l":{"leaf":0},"r":{"f":11,"t":4.52,"l":{"f":13,"t":0.5,"l":{"leaf":0},"r":{"leaf":1}},"r":{"f":41,"t":2,"l":{"leaf":0.6923076923076923},"r":{"f":24,"t":0.5,"l":{"leaf":1},"r":{"leaf":0.75}}}}},"r":{"leaf":0}}},{"f":4,"t":0.5,"l":{"f":32,"t":0.5,"l":{"f":22,"t":0.5,"l":{"f":41,"t":4,"l":{"f":28,"t":1.5,"l":{"f":41,"t":1.5,"l":{"leaf":0.4},"r":{"leaf":0}},"r":{"f":23,"t":0.5,"l":{"leaf":0.6944444444444444},"r":{"leaf":0.6666666666666666}}},"r":{"f":30,"t":0.5,"l":{"leaf":0},"r":{"f":28,"t":1,"l":{"leaf":0},"r":{"leaf":0.8391959798994975}}}},"r":{"leaf":0}},"r":{"leaf":0}},"r":{"leaf":0}},{"f":27,"t":0.5,"l":{"leaf":0},"r":{"f":10,"t":14,"l":{"f":0,"t":0.5,"l":{"f":29,"t":0.5,"l":{"leaf":0},"r":{"f":41,"t":43.5,"l":{"leaf":1},"r":{"leaf":0.9545454545454546}}},"r":{"f":5,"t":0.5,"l":{"leaf":1},"r":{"leaf":0}}},"r":{"f":12,"t":1.5,"l":{"f":3,"t":0.5,"l":{"f":10,"t":23,"l":{"f":9,"t":2.5,"l":{"leaf":0.46236559139784944},"r":{"leaf":0.0625}},"r":{"leaf":0}},"r":{"leaf":1}},"r":{"f":5,"t":0.5,"l":{"leaf":1},"r":{"f":18,"t":0.5,"l":{"f":32,"t":0.5,"l":{"leaf":0.9047619047619048},"r":{"leaf":0}},"r":{"leaf":0.6666666666666666}}}}}},{"f":41,"t":4.5,"l":{"f":17,"t":0.5,"l":{"f":0,"t":0.5,"l":{"f":11,"t":1.855,"l":{"leaf":0.5},"r":{"leaf":0}},"r":{"f":11,"t":4.52,"l":{"f":45,"t":0.7,"l":{"leaf":0},"r":{"leaf":1}},"r":{"leaf":1}}},"r":{"leaf":0.42424242424242425}},"r":{"f":29,"t":0.5,"l":{"leaf":0},"r":{"f":13,"t":0.5,"l":{"f":25,"t":0.5,"l":{"f":38,"t":0.5,"l":{"f":27,"t":0.5,"l":{"leaf":0},"r":{"leaf":0.9421965317919075}},"r":{"leaf":0}},"r":{"f":23,"t":0.5,"l":{"f":10,"t":13.5,"l":{"leaf":1},"r":{"leaf":0.8}},"r":{"leaf":1}}},"r":{"leaf":0.16666666666666666}}}},{"f":26,"t":2.5,"l":{"leaf":0},"r":{"f":29,"t":0.5,"l":{"leaf":0},"r":{"f":45,"t":0.6499999999999999,"l":{"f":0,"t":0.5,"l":{"f":12,"t":0.5,"l":{"leaf":0.9594594594594594},"r":{"leaf":0.7142857142857143}},"r":{"f":13,"t":0.5,"l":{"f":10,"t":38.5,"l":{"leaf":0.25},"r":{"leaf":0.7741935483870968}},"r":{"leaf":0}}},"r":{"leaf":1}}}},{"f":29,"t":0.5,"l":{"leaf":0},"r":{"f":31,"t":0.5,"l":{"leaf":0},"r":{"f":16,"t":0.5,"l":{"f":34,"t":0.5,"l":{"f":27,"t":0.5,"l":{"leaf":0},"r":{"f":33,"t":0.5,"l":{"leaf":0.8863636363636364},"r":{"leaf":0}}},"r":{"leaf":0}},"r":{"leaf":0}}}},{"f":27,"t":0.5,"l":{"f":12,"t":1.5,"l":{"leaf":0},"r":{"f":6,"t":0.5,"l":{"leaf":0},"r":{"leaf":1}}},"r":{"f":32,"t":0.5,"l":{"f":16,"t":0.5,"l":{"f":41,"t":30.5,"l":{"f":5,"t":0.5,"l":{"f":11,"t":3.355,"l":{"leaf":0.9384615384615385},"r":{"leaf":0.5263157894736842}},"r":{"f":12,"t":1.5,"l":{"leaf":0.1111111111111111},"r":{"leaf":0.8787878787878788}}},"r":{"f":29,"t":0.5,"l":{"leaf":0},"r":{"f":41,"t":61,"l":{"leaf":1},"r":{"leaf":0.9019607843137255}}}},"r":{"leaf":0}},"r":{"leaf":0}}},{"f":26,"t":2.5,"l":{"f":23,"t":0.5,"l":{"leaf":0},"r":{"f":8,"t":0.5,"l":{"f":9,"t":1,"l":{"leaf":0},"r":{"leaf":1}},"r":{"leaf":0}}},"r":{"f":30,"t":0.5,"l":{"leaf":0},"r":{"f":11,"t":4.79,"l":{"f":11,"t":3.375,"l":{"f":7,"t":0.5,"l":{"f":16,"t":0.5,"l":{"leaf":0.7093023255813954},"r":{"leaf":0}},"r":{"leaf":1}},"r":{"f":42,"t":0.5,"l":{"f":32,"t":0.5,"l":{"leaf":0.36363636363636365},"r":{"leaf":0}},"r":{"f":24,"t":0.5,"l":{"leaf":0.3333333333333333},"r":{"leaf":1}}}},"r":{"leaf":1}}}},{"f":28,"t":1.5,"l":{"leaf":0},"r":{"f":30,"t":0.5,"l":{"leaf":0},"r":{"f":42,"t":0.5,"l":{"f":23,"t":0.5,"l":{"f":45,"t":0.7,"l":{"f":33,"t":0.5,"l":{"leaf":0.37142857142857144},"r":{"leaf":0}},"r":{"leaf":1}},"r":{"f":10,"t":151,"l":{"leaf":0.5},"r":{"leaf":1}}},"r":{"f":29,"t":0.5,"l":{"leaf":0},"r":{"f":16,"t":0.5,"l":{"f":3,"t":0.5,"l":{"leaf":0.9197530864197531},"r":{"leaf":1}},"r":{"leaf":0}}}}}},{"f":31,"t":0.5,"l":{"leaf":0},"r":{"f":36,"t":0.5,"l":{"f":41,"t":4.5,"l":{"f":11,"t":4.615,"l":{"f":12,"t":0.5,"l":{"f":41,"t":2.5,"l":{"leaf":0.8333333333333334},"r":{"leaf":0.16666666666666666}},"r":{"f":45,"t":0.7,"l":{"leaf":0.12121212121212122},"r":{"leaf":1}}},"r":{"f":6,"t":0.5,"l":{"leaf":0.6666666666666666},"r":{"leaf":1}}},"r":{"f":30,"t":0.5,"l":{"leaf":0},"r":{"f":27,"t":0.5,"l":{"leaf":0},"r":{"f":3,"t":0.5,"l":{"leaf":0.8064516129032258},"r":{"leaf":1}}}}},"r":{"leaf":0}}},{"f":29,"t":0.5,"l":{"leaf":0},"r":{"f":3,"t":0.5,"l":{"f":4,"t":0.5,"l":{"f":28,"t":1.5,"l":{"f":10,"t":17.5,"l":{"leaf":0},"r":{"leaf":0.5}},"r":{"f":42,"t":0.5,"l":{"f":11,"t":4.665,"l":{"leaf":0.36363636363636365},"r":{"leaf":0.9047619047619048}},"r":{"f":31,"t":0.5,"l":{"leaf":0},"r":{"leaf":0.9230769230769231}}}},"r":{"leaf":0}},"r":{"f":42,"t":0.5,"l":{"leaf":0},"r":{"f":27,"t":0.5,"l":{"leaf":0},"r":{"leaf":1}}}}}],"meta":{"nTrees":150,"maxDepth":6,"minLeaf":2,"featureSubset":7,"dim":46,"samples":345}}